[{"店铺id":"必填","分类名称":"必填\n10个字以内","商品名称":"必填\n30个字以内","价格":"必填\n填写数字","餐盒数量":"0-100","餐盒价格":"0-100","最小购买量":"0-50","折扣价格":"","折扣限购":""},{"店铺id":"8591999","分类名称":"甜糯汤圆","商品名称":"汤圆绿豆沙","价格":"13.8","餐盒数量":"1","餐盒价格":"1","最小购买量":"1","折扣价格":"","折扣限购":""},{"店铺id":"8591999","分类名称":"甜糯汤圆","商品名称":"椰奶汤圆","价格":"13.8","餐盒数量":"1","餐盒价格":"1","最小购买量":"1","折扣价格":"","折扣限购":""},{"店铺id":"8591999","分类名称":"甜糯汤圆","商品名称":"汤圆椰汁西米露","价格":"13.8","餐盒数量":"1","餐盒价格":"1","最小购买量":"1","折扣价格":"","折扣限购":""},{"店铺id":"8591999","分类名称":"甜糯汤圆","商品名称":"汤圆红豆沙","价格":"13.8","餐盒数量":"1","餐盒价格":"1","最小购买量":"1","折扣价格":"","折扣限购":""},{"店铺id":"8591999","分类名称":"甜糯汤圆","商品名称":"清水汤圆【8颗】$","价格":"13.8","餐盒数量":"1","餐盒价格":"1","最小购买量":"1","折扣价格":"","折扣限购":""},{"店铺id":"8591999","分类名称":"必抢折扣","商品名称":"熊猫果茶(推荐)$","价格":"14.8","餐盒数量":"1","餐盒价格":"1","最小购买量":"1","折扣价格":"12.8","折扣限购":""},{"店铺id":"8591999","分类名称":"风味小吃","商品名称":"香芋地瓜丸【6个】","价格":"13.8","餐盒数量":"1","餐盒价格":"1","最小购买量":"1","折扣价格":"","折扣限购":""},{"店铺id":"8591999","分类名称":"风味小吃","商品名称":"上校鸡块(5块)","价格":"13.8","餐盒数量":"1","餐盒价格":"1","最小购买量":"1","折扣价格":"","折扣限购":""},{"店铺id":"8591999","分类名称":"风味小吃","商品名称":"炸墨鱼丸【4个】","价格":"13.8","餐盒数量":"1","餐盒价格":"1","最小购买量":"1","折扣价格":"","折扣限购":""},{"店铺id":"8591999","分类名称":"风味小吃","商品名称":"咖喱鱼丸【6个】","价格":"13.8","餐盒数量":"1","餐盒价格":"1","最小购买量":"1","折扣价格":"","折扣限购":""},{"店铺id":"8591999","分类名称":"风味小吃","商品名称":"牛筋丸(5个)","价格":"13.8","餐盒数量":"1","餐盒价格":"1","最小购买量":"1","折扣价格":"","折扣限购":""},{"店铺id":"8591999","分类名称":"风味小吃","商品名称":"日式章鱼小丸子【4个】","价格":"13.8","餐盒数量":"1","餐盒价格":"1","最小购买量":"1","折扣价格":"","折扣限购":""},{"店铺id":"8591999","分类名称":"风味小吃","商品名称":"骨肉相连(3串)","价格":"13.8","餐盒数量":"1","餐盒价格":"1","最小购买量":"1","折扣价格":"","折扣限购":""},{"店铺id":"8591999","分类名称":"风味小吃","商品名称":"正宗重庆酸辣粉【麻辣酸爽】","价格":"13.8","餐盒数量":"1","餐盒价格":"1","最小购买量":"1","折扣价格":"","折扣限购":""},{"店铺id":"8591999","分类名称":"精选奶茶","商品名称":"原味奶茶(纯奶茶)","价格":"13.8","餐盒数量":"1","餐盒价格":"1","最小购买量":"1","折扣价格":"","折扣限购":""},{"店铺id":"8591999","分类名称":"必抢折扣","商品名称":"招牌珍珠奶茶【大杯】$","价格":"13.8","餐盒数量":"1","餐盒价格":"1","最小购买量":"1","折扣价格":"","折扣限购":""},{"店铺id":"8591999","分类名称":"台湾手抓饼","商品名称":"台湾手抓饼(双拼)","价格":"13.8","餐盒数量":"1","餐盒价格":"1","最小购买量":"1","折扣价格":"","折扣限购":""},{"店铺id":"8828359","分类名称":"必抢折扣","商品名称":"芝士焗番薯$","价格":"13.8","餐盒数量":"1","餐盒价格":"1","最小购买量":"1","折扣价格":"10.8","折扣限购":""},{"店铺id":"8828359","分类名称":"必抢折扣","商品名称":"炸薯条$(必抢)","价格":"13.8","餐盒数量":"1","餐盒价格":"1","最小购买量":"1","折扣价格":"7.8","折扣限购":""},{"店铺id":"8828359","分类名称":"必抢折扣","商品名称":"杨枝甘露$","价格":"13.8","餐盒数量":"1","餐盒价格":"1","最小购买量":"1","折扣价格":"11.8","折扣限购":""},{"店铺id":"8828359","分类名称":"必抢折扣","商品名称":"招牌鲜肉锅盔(鲜香)","价格":"13.8","餐盒数量":"1","餐盒价格":"1","最小购买量":"1","折扣价格":"7.9","折扣限购":""},{"店铺id":"8828359","分类名称":"必抢折扣","商品名称":"多芒小丸子【必抢】$","价格":"13.8","餐盒数量":"1","餐盒价格":"1","最小购买量":"1","折扣价格":"10.8","折扣限购":""},{"店铺id":"8828359","分类名称":"必抢折扣","商品名称":"招牌梅干菜锅盔(推荐)","价格":"13.8","餐盒数量":"1","餐盒价格":"1","最小购买量":"1","折扣价格":"7.9","折扣限购":""},{"店铺id":"8828359","分类名称":"必抢折扣","商品名称":"香港车仔面","价格":"13.8","餐盒数量":"1","餐盒价格":"1","最小购买量":"1","折扣价格":"8.8","折扣限购":""},{"店铺id":"8828359","分类名称":"必抢折扣","商品名称":"芋圆椰奶烧仙草【不点后悔终身】$","价格":"13.8","餐盒数量":"1","餐盒价格":"1","最小购买量":"1","折扣价格":"9.6","折扣限购":""},{"店铺id":"8828359","分类名称":"必抢折扣","商品名称":"日式章鱼小丸子4个(风靡)$","价格":"13.8","餐盒数量":"1","餐盒价格":"1","最小购买量":"1","折扣价格":"7.9","折扣限购":""},{"店铺id":"8828359","分类名称":"必抢折扣","商品名称":"招牌烧仙草【超多料在里面】$","价格":"13.8","餐盒数量":"1","餐盒价格":"1","最小购买量":"1","折扣价格":"8.8","折扣限购":""},{"店铺id":"8828359","分类名称":"必抢折扣","商品名称":"正宗重庆酸辣粉【麻辣酸爽】$(必抢)","价格":"13.8","餐盒数量":"1","餐盒价格":"1","最小购买量":"1","折扣价格":"8.8","折扣限购":""},{"店铺id":"8828359","分类名称":"甜糯汤圆","商品名称":"汤圆绿豆沙","价格":"13.8","餐盒数量":"1","餐盒价格":"1","最小购买量":"1","折扣价格":"9.9","折扣限购":""},{"店铺id":"8828359","分类名称":"甜糯汤圆","商品名称":"汤圆红豆沙","价格":"13.8","餐盒数量":"1","餐盒价格":"1","最小购买量":"1","折扣价格":"9.9","折扣限购":""},{"店铺id":"8828359","分类名称":"甜糯汤圆","商品名称":"汤圆椰汁西米露","价格":"13.8","餐盒数量":"1","餐盒价格":"1","最小购买量":"1","折扣价格":"10.9","折扣限购":""},{"店铺id":"8828359","分类名称":"甜糯汤圆","商品名称":"椰奶汤圆","价格":"13.8","餐盒数量":"1","餐盒价格":"1","最小购买量":"1","折扣价格":"10.9","折扣限购":""},{"店铺id":"8828359","分类名称":"豆沙系列","商品名称":"西米红豆沙","价格":"13.8","餐盒数量":"1","餐盒价格":"1","最小购买量":"1","折扣价格":"","折扣限购":""},{"店铺id":"8828359","分类名称":"豆沙系列","商品名称":"西米绿豆沙","价格":"13.8","餐盒数量":"1","餐盒价格":"1","最小购买量":"1","折扣价格":"","折扣限购":""},{"店铺id":"8828359","分类名称":"必抢折扣","商品名称":"【热销】螺蛳粉$","价格":"13.8","餐盒数量":"1","餐盒价格":"1","最小购买量":"1","折扣价格":"11.8","折扣限购":""},{"店铺id":"8828359","分类名称":"豆沙系列","商品名称":"香芋红豆沙","价格":"13.8","餐盒数量":"1","餐盒价格":"1","最小购买量":"1","折扣价格":"","折扣限购":""},{"店铺id":"8828359","分类名称":"豆沙系列","商品名称":"香芋绿豆沙","价格":"13.8","餐盒数量":"1","餐盒价格":"1","最小购买量":"1","折扣价格":"","折扣限购":""},{"店铺id":"8828359","分类名称":"豆沙系列","商品名称":"芋圆绿豆沙","价格":"13.8","餐盒数量":"1","餐盒价格":"1","最小购买量":"1","折扣价格":"","折扣限购":""},{"店铺id":"8828359","分类名称":"豆沙系列","商品名称":"芋圆红豆沙","价格":"13.8","餐盒数量":"1","餐盒价格":"1","最小购买量":"1","折扣价格":"","折扣限购":""},{"店铺id":"8828359","分类名称":"豆沙系列","商品名称":"绿豆沙$","价格":"13.8","餐盒数量":"1","餐盒价格":"1","最小购买量":"1","折扣价格":"3.88","折扣限购":"1"},{"店铺id":"8828359","分类名称":"龟苓膏类","商品名称":"蜂蜜龟苓膏","价格":"13.8","餐盒数量":"1","餐盒价格":"1","最小购买量":"1","折扣价格":"","折扣限购":""},{"店铺id":"8828359","分类名称":"龟苓膏类","商品名称":"红豆龟苓膏","价格":"13.8","餐盒数量":"1","餐盒价格":"1","最小购买量":"1","折扣价格":"","折扣限购":""},{"店铺id":"8828359","分类名称":"龟苓膏类","商品名称":"椰奶龟苓膏","价格":"13.8","餐盒数量":"1","餐盒价格":"1","最小购买量":"1","折扣价格":"","折扣限购":""},{"店铺id":"8828359","分类名称":"龟苓膏类","商品名称":"炼奶龟苓膏","价格":"13.8","餐盒数量":"1","餐盒价格":"1","最小购买量":"1","折扣价格":"","折扣限购":""},{"店铺id":"8828359","分类名称":"西米系列","商品名称":"莲子椰汁西米露","价格":"13.8","餐盒数量":"1","餐盒价格":"1","最小购买量":"1","折扣价格":"","折扣限购":""},{"店铺id":"8828359","分类名称":"西米系列","商品名称":"木瓜椰汁西米露","价格":"13.8","餐盒数量":"1","餐盒价格":"1","最小购买量":"1","折扣价格":"","折扣限购":""},{"店铺id":"8828359","分类名称":"西米系列","商品名称":"椰汁西米露","价格":"13.8","餐盒数量":"1","餐盒价格":"1","最小购买量":"1","折扣价格":"","折扣限购":""},{"店铺id":"8828359","分类名称":"西米系列","商品名称":"芋圆红豆椰汁西米露","价格":"13.8","餐盒数量":"1","餐盒价格":"1","最小购买量":"1","折扣价格":"","折扣限购":""},{"店铺id":"8828359","分类名称":"西米系列","商品名称":"香芋椰汁西米露","价格":"13.8","餐盒数量":"1","餐盒价格":"1","最小购买量":"1","折扣价格":"","折扣限购":""},{"店铺id":"8828359","分类名称":"西米系列","商品名称":"芋圆椰汁西米露","价格":"13.8","餐盒数量":"1","餐盒价格":"1","最小购买量":"1","折扣价格":"","折扣限购":""},{"店铺id":"8828359","分类名称":"西米系列","商品名称":"芒果椰汁西米露","价格":"13.8","餐盒数量":"1","餐盒价格":"1","最小购买量":"1","折扣价格":"","折扣限购":""},{"店铺id":"8828359","分类名称":"鲜奶系列","商品名称":"鲜奶香芋","价格":"13.8","餐盒数量":"1","餐盒价格":"1","最小购买量":"1","折扣价格":"","折扣限购":""},{"店铺id":"8828359","分类名称":"鲜奶系列","商品名称":"芒果鲜奶","价格":"13.8","餐盒数量":"1","餐盒价格":"1","最小购买量":"1","折扣价格":"","折扣限购":""},{"店铺id":"8828359","分类名称":"鲜奶系列","商品名称":"鲜奶红豆番薯糖水","价格":"13.8","餐盒数量":"1","餐盒价格":"1","最小购买量":"1","折扣价格":"","折扣限购":""},{"店铺id":"8828359","分类名称":"鲜奶系列","商品名称":"木瓜鲜奶","价格":"13.8","餐盒数量":"1","餐盒价格":"1","最小购买量":"1","折扣价格":"","折扣限购":""},{"店铺id":"8828359","分类名称":"鲜奶系列","商品名称":"鲜奶红豆","价格":"13.8","餐盒数量":"1","餐盒价格":"1","最小购买量":"1","折扣价格":"","折扣限购":""},{"店铺id":"8828359","分类名称":"肉馅锅盔","商品名称":"招牌梅干菜锅盔(推荐)","价格":"13.8","餐盒数量":"1","餐盒价格":"1","最小购买量":"1","折扣价格":"7.9","折扣限购":""},{"店铺id":"8828359","分类名称":"肉馅锅盔","商品名称":"招牌鲜肉锅盔(鲜香)","价格":"13.8","餐盒数量":"1","餐盒价格":"1","最小购买量":"1","折扣价格":"7.9","折扣限购":""},{"店铺id":"8828359","分类名称":"养颜桃胶","商品名称":"桃胶椰汁西米露","价格":"13.8","餐盒数量":"1","餐盒价格":"1","最小购买量":"1","折扣价格":"","折扣限购":""},{"店铺id":"8828359","分类名称":"双皮奶类","商品名称":"莲子双皮奶","价格":"13.8","餐盒数量":"1","餐盒价格":"1","最小购买量":"1","折扣价格":"","折扣限购":""},{"店铺id":"8828359","分类名称":"养颜桃胶","商品名称":"桃胶绿豆沙","价格":"13.8","餐盒数量":"1","餐盒价格":"1","最小购买量":"1","折扣价格":"","折扣限购":""},{"店铺id":"8828359","分类名称":"双皮奶类","商品名称":"红豆双皮奶","价格":"13.8","餐盒数量":"1","餐盒价格":"1","最小购买量":"1","折扣价格":"","折扣限购":""},{"店铺id":"8828359","分类名称":"双皮奶类","商品名称":"芋圆双皮奶","价格":"13.8","餐盒数量":"1","餐盒价格":"1","最小购买量":"1","折扣价格":"","折扣限购":""},{"店铺id":"8828359","分类名称":"养颜桃胶","商品名称":"雪耳桃胶羹","价格":"13.8","餐盒数量":"1","餐盒价格":"1","最小购买量":"1","折扣价格":"","折扣限购":""},{"店铺id":"8828359","分类名称":"双皮奶类","商品名称":"芒果双皮奶","价格":"13.8","餐盒数量":"1","餐盒价格":"1","最小购买量":"1","折扣价格":"","折扣限购":""},{"店铺id":"8828359","分类名称":"养颜桃胶","商品名称":"鲜奶炖桃胶【女神必点！！】$","价格":"13.8","餐盒数量":"1","餐盒价格":"1","最小购买量":"1","折扣价格":"7.8","折扣限购":""},{"店铺id":"8828359","分类名称":"养颜桃胶","商品名称":"【至尊】木瓜雪耳桃胶炖鲜奶$","价格":"13.8","餐盒数量":"1","餐盒价格":"1","最小购买量":"1","折扣价格":"8.9","折扣限购":""},{"店铺id":"8828359","分类名称":"双皮奶类","商品名称":"奥利奥双皮奶【新品推荐】","价格":"13.8","餐盒数量":"1","餐盒价格":"1","最小购买量":"1","折扣价格":"9.9","折扣限购":""},{"店铺id":"8828359","分类名称":"风味小吃","商品名称":"香芋地瓜丸【6个】","价格":"13.8","餐盒数量":"1","餐盒价格":"1","最小购买量":"1","折扣价格":"","折扣限购":""},{"店铺id":"8828359","分类名称":"风味小吃","商品名称":"深海墨鱼丸【4个】","价格":"13.8","餐盒数量":"1","餐盒价格":"1","最小购买量":"1","折扣价格":"","折扣限购":""},{"店铺id":"8828359","分类名称":"风味小吃","商品名称":"炸双皮奶【3个】","价格":"13.8","餐盒数量":"1","餐盒价格":"1","最小购买量":"1","折扣价格":"","折扣限购":""},{"店铺id":"8828359","分类名称":"风味小吃","商品名称":"泰香虾饼【2个】","价格":"13.8","餐盒数量":"1","餐盒价格":"1","最小购买量":"1","折扣价格":"","折扣限购":""},{"店铺id":"8828359","分类名称":"风味小吃","商品名称":"潮汕牛筋丸【5个】","价格":"13.8","餐盒数量":"1","餐盒价格":"1","最小购买量":"1","折扣价格":"","折扣限购":""},{"店铺id":"8828359","分类名称":"风味小吃","商品名称":"骨肉相连【3串】","价格":"13.8","餐盒数量":"1","餐盒价格":"1","最小购买量":"1","折扣价格":"","折扣限购":""},{"店铺id":"8828359","分类名称":"风味小吃","商品名称":"上校鸡块(5块)","价格":"13.8","餐盒数量":"1","餐盒价格":"1","最小购买量":"1","折扣价格":"","折扣限购":""},{"店铺id":"8828359","分类名称":"风味小吃","商品名称":"川香鸡柳【2根】","价格":"13.8","餐盒数量":"1","餐盒价格":"1","最小购买量":"1","折扣价格":"","折扣限购":""},{"店铺id":"8828359","分类名称":"风味小吃","商品名称":"炸薯条","价格":"13.8","餐盒数量":"1","餐盒价格":"1","最小购买量":"1","折扣价格":"","折扣限购":""},{"店铺id":"8828359","分类名称":"风味小吃","商品名称":"咖喱鱼丸【6个】","价格":"13.8","餐盒数量":"1","餐盒价格":"1","最小购买量":"1","折扣价格":"","折扣限购":""},{"店铺id":"8828359","分类名称":"风味小吃","商品名称":"香港车仔面","价格":"13.8","餐盒数量":"1","餐盒价格":"1","最小购买量":"1","折扣价格":"8.8","折扣限购":""},{"店铺id":"8828359","分类名称":"风味小吃","商品名称":"台湾盐酥鸡","价格":"13.8","餐盒数量":"1","餐盒价格":"1","最小购买量":"1","折扣价格":"","折扣限购":""},{"店铺id":"8828359","分类名称":"风味小吃","商品名称":"长沙臭豆腐","价格":"13.8","餐盒数量":"1","餐盒价格":"1","最小购买量":"1","折扣价格":"","折扣限购":""},{"店铺id":"8828359","分类名称":"风味小吃","商品名称":"正宗重庆酸辣粉【麻辣酸爽】","价格":"13.8","餐盒数量":"1","餐盒价格":"1","最小购买量":"1","折扣价格":"","折扣限购":""},{"店铺id":"8828359","分类名称":"风味小吃","商品名称":"日式章鱼小丸子【4个】","价格":"13.8","餐盒数量":"1","餐盒价格":"1","最小购买量":"1","折扣价格":"","折扣限购":""},{"店铺id":"8828359","分类名称":"风味小吃","商品名称":"爆浆糍粑(3根)","价格":"13.8","餐盒数量":"1","餐盒价格":"1","最小购买量":"1","折扣价格":"","折扣限购":""},{"店铺id":"8828359","分类名称":"韩式烤冷面","商品名称":"香葱烤冷面","价格":"13.8","餐盒数量":"1","餐盒价格":"1","最小购买量":"1","折扣价格":"","折扣限购":""},{"店铺id":"8828359","分类名称":"韩式烤冷面","商品名称":"肉松烤冷面【酸甜味】","价格":"13.8","餐盒数量":"1","餐盒价格":"1","最小购买量":"1","折扣价格":"","折扣限购":""},{"店铺id":"8828359","分类名称":"韩式烤冷面","商品名称":"双蛋烤冷面","价格":"13.8","餐盒数量":"1","餐盒价格":"1","最小购买量":"1","折扣价格":"","折扣限购":""},{"店铺id":"8828359","分类名称":"韩式烤冷面","商品名称":"培根烤冷面","价格":"13.8","餐盒数量":"1","餐盒价格":"1","最小购买量":"1","折扣价格":"","折扣限购":""},{"店铺id":"8828359","分类名称":"台湾手抓饼","商品名称":"台湾手抓饼(双拼)","价格":"13.8","餐盒数量":"1","餐盒价格":"1","最小购买量":"1","折扣价格":"","折扣限购":""},{"店铺id":"8828359","分类名称":"台湾手抓饼","商品名称":"台湾手抓饼(三拼)","价格":"13.8","餐盒数量":"1","餐盒价格":"1","最小购买量":"1","折扣价格":"","折扣限购":""},{"店铺id":"8828359","分类名称":"嫩滑仙草","商品名称":"酸奶烧仙草","价格":"13.8","餐盒数量":"1","餐盒价格":"1","最小购买量":"1","折扣价格":"","折扣限购":""},{"店铺id":"8828359","分类名称":"嫩滑仙草","商品名称":"椰奶烧仙草","价格":"13.8","餐盒数量":"1","餐盒价格":"1","最小购买量":"1","折扣价格":"","折扣限购":""},{"店铺id":"8828359","分类名称":"手工芋圆","商品名称":"多芒小丸子","价格":"13.8","餐盒数量":"1","餐盒价格":"1","最小购买量":"1","折扣价格":"","折扣限购":""},{"店铺id":"9365870","分类名称":"必抢折扣","商品名称":"韩式年糕","价格":"13.8","餐盒数量":"1","餐盒价格":"1","最小购买量":"1","折扣价格":"8.8","折扣限购":""},{"店铺id":"9365870","分类名称":"精选奶茶","商品名称":"黑钻奶茶","价格":"13.8","餐盒数量":"1","餐盒价格":"1","最小购买量":"1","折扣价格":"","折扣限购":""},{"店铺id":"9365870","分类名称":"精选奶茶","商品名称":"冲绳黑钻霸","价格":"13.8","餐盒数量":"1","餐盒价格":"1","最小购买量":"1","折扣价格":"","折扣限购":""},{"店铺id":"9365870","分类名称":"精选奶茶","商品名称":"茶香奶绿","价格":"13.8","餐盒数量":"1","餐盒价格":"1","最小购买量":"1","折扣价格":"","折扣限购":""},{"店铺id":"9365870","分类名称":"精选奶茶","商品名称":"北海布丁秀","价格":"13.8","餐盒数量":"1","餐盒价格":"1","最小购买量":"1","折扣价格":"","折扣限购":""},{"店铺id":"9365870","分类名称":"精选奶茶","商品名称":"香米阿华田","价格":"13.8","餐盒数量":"1","餐盒价格":"1","最小购买量":"1","折扣价格":"","折扣限购":""},{"店铺id":"9365870","分类名称":"精选奶茶","商品名称":"仙草冻奶茶","价格":"13.8","餐盒数量":"1","餐盒价格":"1","最小购买量":"1","折扣价格":"","折扣限购":""},{"店铺id":"9365870","分类名称":"精选奶茶","商品名称":"布丁奶茶","价格":"13.8","餐盒数量":"1","餐盒价格":"1","最小购买量":"1","折扣价格":"","折扣限购":""},{"店铺id":"9365870","分类名称":"精选奶茶","商品名称":"香米椰奶红豆","价格":"13.8","餐盒数量":"1","餐盒价格":"1","最小购买量":"1","折扣价格":"","折扣限购":""},{"店铺id":"9365870","分类名称":"精选奶茶","商品名称":"碳烧黑糖冻奶茶","价格":"13.8","餐盒数量":"1","餐盒价格":"1","最小购买量":"1","折扣价格":"","折扣限购":""},{"店铺id":"9365870","分类名称":"精选奶茶","商品名称":"金时布丁抹茶","价格":"13.8","餐盒数量":"1","餐盒价格":"1","最小购买量":"1","折扣价格":"","折扣限购":""},{"店铺id":"9365870","分类名称":"精选奶茶","商品名称":"金钻奶茶","价格":"13.8","餐盒数量":"1","餐盒价格":"1","最小购买量":"1","折扣价格":"","折扣限购":""},{"店铺id":"9365870","分类名称":"精选奶茶","商品名称":"原味奶茶(纯奶茶)","价格":"13.8","餐盒数量":"1","餐盒价格":"1","最小购买量":"1","折扣价格":"","折扣限购":""},{"店铺id":"9365870","分类名称":"精选奶茶","商品名称":"双拼奶茶","价格":"13.8","餐盒数量":"1","餐盒价格":"1","最小购买量":"1","折扣价格":"","折扣限购":""},{"店铺id":"9365870","分类名称":"精选奶茶","商品名称":"香米抹茶红豆","价格":"13.8","餐盒数量":"1","餐盒价格":"1","最小购买量":"1","折扣价格":"","折扣限购":""},{"店铺id":"9365870","分类名称":"精选奶茶","商品名称":"奥利奥奶茶","价格":"13.8","餐盒数量":"1","餐盒价格":"1","最小购买量":"1","折扣价格":"","折扣限购":""},{"店铺id":"9365870","分类名称":"精选奶茶","商品名称":"格雷三兄弟","价格":"13.8","餐盒数量":"1","餐盒价格":"1","最小购买量":"1","折扣价格":"","折扣限购":""},{"店铺id":"9365870","分类名称":"精选奶茶","商品名称":"椰果奶茶","价格":"13.8","餐盒数量":"1","餐盒价格":"1","最小购买量":"1","折扣价格":"","折扣限购":""},{"店铺id":"9365870","分类名称":"精选奶茶","商品名称":"红豆布丁奶茶","价格":"13.8","餐盒数量":"1","餐盒价格":"1","最小购买量":"1","折扣价格":"","折扣限购":""},{"店铺id":"9365870","分类名称":"精选奶茶","商品名称":"波霸珍珠奶茶","价格":"13.8","餐盒数量":"1","餐盒价格":"1","最小购买量":"1","折扣价格":"","折扣限购":""},{"店铺id":"9365870","分类名称":"精选奶茶","商品名称":"招牌烧仙草(料多好味道)","价格":"13.8","餐盒数量":"1","餐盒价格":"1","最小购买量":"1","折扣价格":"","折扣限购":""},{"店铺id":"9365870","分类名称":"风味小吃","商品名称":"炸墨鱼丸【4个】","价格":"13.8","餐盒数量":"1","餐盒价格":"1","最小购买量":"1","折扣价格":"","折扣限购":""},{"店铺id":"9365870","分类名称":"风味小吃","商品名称":"牛筋丸(5个)","价格":"13.8","餐盒数量":"1","餐盒价格":"1","最小购买量":"1","折扣价格":"","折扣限购":""},{"店铺id":"9365870","分类名称":"风味小吃","商品名称":"上校鸡块(5块)","价格":"13.8","餐盒数量":"1","餐盒价格":"1","最小购买量":"1","折扣价格":"","折扣限购":""},{"店铺id":"9365870","分类名称":"风味小吃","商品名称":"骨肉相连(3串)","价格":"13.8","餐盒数量":"1","餐盒价格":"1","最小购买量":"1","折扣价格":"","折扣限购":""},{"店铺id":"9365870","分类名称":"风味小吃","商品名称":"咖喱鱼丸【6个】","价格":"13.8","餐盒数量":"1","餐盒价格":"1","最小购买量":"1","折扣价格":"","折扣限购":""},{"店铺id":"9365870","分类名称":"风味小吃","商品名称":"香芋地瓜丸【6个】","价格":"13.8","餐盒数量":"1","餐盒价格":"1","最小购买量":"1","折扣价格":"","折扣限购":""},{"店铺id":"9365870","分类名称":"风味小吃","商品名称":"日式章鱼小丸子【4个】","价格":"13.8","餐盒数量":"1","餐盒价格":"1","最小购买量":"1","折扣价格":"","折扣限购":""},{"店铺id":"9365870","分类名称":"风味小吃","商品名称":"台湾盐酥鸡","价格":"13.8","餐盒数量":"1","餐盒价格":"1","最小购买量":"1","折扣价格":"","折扣限购":""},{"店铺id":"9365870","分类名称":"风味小吃","商品名称":"正宗重庆酸辣粉【麻辣酸爽】","价格":"13.8","餐盒数量":"1","餐盒价格":"1","最小购买量":"1","折扣价格":"","折扣限购":""},{"店铺id":"9365870","分类名称":"韩式烤冷面","商品名称":"肉松烤冷面","价格":"13.8","餐盒数量":"1","餐盒价格":"1","最小购买量":"1","折扣价格":"","折扣限购":""},{"店铺id":"9365870","分类名称":"韩式烤冷面","商品名称":"香葱烤冷面","价格":"13.8","餐盒数量":"1","餐盒价格":"1","最小购买量":"1","折扣价格":"","折扣限购":""},{"店铺id":"9365870","分类名称":"韩式烤冷面","商品名称":"双蛋烤冷面","价格":"13.8","餐盒数量":"1","餐盒价格":"1","最小购买量":"1","折扣价格":"","折扣限购":""},{"店铺id":"9365870","分类名称":"风味小吃","商品名称":"炸牛奶【3个】","价格":"13.8","餐盒数量":"1","餐盒价格":"1","最小购买量":"1","折扣价格":"","折扣限购":""},{"店铺id":"9365870","分类名称":"韩式烤冷面","商品名称":"培根烤冷面","价格":"13.8","餐盒数量":"1","餐盒价格":"1","最小购买量":"1","折扣价格":"","折扣限购":""},{"店铺id":"9365870","分类名称":"台湾手抓饼","商品名称":"台湾手抓饼(双拼)","价格":"13.8","餐盒数量":"1","餐盒价格":"1","最小购买量":"1","折扣价格":"","折扣限购":""},{"店铺id":"9365870","分类名称":"台湾手抓饼","商品名称":"台湾手抓饼(三拼)","价格":"13.8","餐盒数量":"1","餐盒价格":"1","最小购买量":"1","折扣价格":"","折扣限购":""},{"店铺id":"9411146","分类名称":"必抢折扣","商品名称":"香港车仔面","价格":"13.8","餐盒数量":"1","餐盒价格":"1","最小购买量":"1","折扣价格":"8.8","折扣限购":""},{"店铺id":"9411146","分类名称":"必抢折扣","商品名称":"芋圆椰奶烧仙草【不点后悔终身】$","价格":"13.8","餐盒数量":"1","餐盒价格":"1","最小购买量":"1","折扣价格":"8.9","折扣限购":""},{"店铺id":"9411146","分类名称":"必抢折扣","商品名称":"炸薯条$(必抢)","价格":"13.8","餐盒数量":"1","餐盒价格":"1","最小购买量":"1","折扣价格":"7.8","折扣限购":""},{"店铺id":"9411146","分类名称":"豆沙系列","商品名称":"芋圆红豆沙","价格":"13.8","餐盒数量":"1","餐盒价格":"1","最小购买量":"1","折扣价格":"","折扣限购":""},{"店铺id":"9411146","分类名称":"豆沙系列","商品名称":"西米红豆沙","价格":"13.8","餐盒数量":"1","餐盒价格":"1","最小购买量":"1","折扣价格":"","折扣限购":""},{"店铺id":"9411146","分类名称":"西米系列","商品名称":"木瓜椰汁西米露","价格":"13.8","餐盒数量":"1","餐盒价格":"1","最小购买量":"1","折扣价格":"","折扣限购":""},{"店铺id":"9411146","分类名称":"豆沙系列","商品名称":"香芋绿豆沙","价格":"13.8","餐盒数量":"1","餐盒价格":"1","最小购买量":"1","折扣价格":"","折扣限购":""},{"店铺id":"9411146","分类名称":"西米系列","商品名称":"莲子椰汁西米露","价格":"13.8","餐盒数量":"1","餐盒价格":"1","最小购买量":"1","折扣价格":"","折扣限购":""},{"店铺id":"9411146","分类名称":"龟苓膏类","商品名称":"红豆龟苓膏","价格":"13.8","餐盒数量":"1","餐盒价格":"1","最小购买量":"1","折扣价格":"","折扣限购":""},{"店铺id":"9411146","分类名称":"豆沙系列","商品名称":"西米绿豆沙","价格":"13.8","餐盒数量":"1","餐盒价格":"1","最小购买量":"1","折扣价格":"","折扣限购":""},{"店铺id":"9411146","分类名称":"西米系列","商品名称":"椰汁西米露","价格":"13.8","餐盒数量":"1","餐盒价格":"1","最小购买量":"1","折扣价格":"","折扣限购":""},{"店铺id":"9411146","分类名称":"龟苓膏类","商品名称":"椰奶龟苓膏","价格":"13.8","餐盒数量":"1","餐盒价格":"1","最小购买量":"1","折扣价格":"","折扣限购":""},{"店铺id":"9411146","分类名称":"豆沙系列","商品名称":"香芋红豆沙","价格":"13.8","餐盒数量":"1","餐盒价格":"1","最小购买量":"1","折扣价格":"","折扣限购":""},{"店铺id":"9411146","分类名称":"西米系列","商品名称":"芋圆椰汁西米露","价格":"13.8","餐盒数量":"1","餐盒价格":"1","最小购买量":"1","折扣价格":"","折扣限购":""},{"店铺id":"9411146","分类名称":"龟苓膏类","商品名称":"炼奶龟苓膏","价格":"13.8","餐盒数量":"1","餐盒价格":"1","最小购买量":"1","折扣价格":"","折扣限购":""},{"店铺id":"9411146","分类名称":"西米系列","商品名称":"芒果椰汁西米露","价格":"13.8","餐盒数量":"1","餐盒价格":"1","最小购买量":"1","折扣价格":"","折扣限购":""},{"店铺id":"9411146","分类名称":"龟苓膏类","商品名称":"蜂蜜龟苓膏","价格":"13.8","餐盒数量":"1","餐盒价格":"1","最小购买量":"1","折扣价格":"","折扣限购":""},{"店铺id":"9411146","分类名称":"豆沙系列","商品名称":"绿豆沙/红豆沙$(单点不送)","价格":"13.8","餐盒数量":"1","餐盒价格":"1","最小购买量":"1","折扣价格":"3.99","折扣限购":""},{"店铺id":"9411146","分类名称":"西米系列","商品名称":"芋圆红豆椰汁西米露","价格":"13.8","餐盒数量":"1","餐盒价格":"1","最小购买量":"1","折扣价格":"","折扣限购":""},{"店铺id":"9411146","分类名称":"西米系列","商品名称":"香芋椰汁西米露","价格":"13.8","餐盒数量":"1","餐盒价格":"1","最小购买量":"1","折扣价格":"","折扣限购":""},{"店铺id":"9411146","分类名称":"鲜奶系列","商品名称":"芒果鲜奶","价格":"13.8","餐盒数量":"1","餐盒价格":"1","最小购买量":"1","折扣价格":"","折扣限购":""},{"店铺id":"9411146","分类名称":"鲜奶系列","商品名称":"鲜奶红豆番薯糖水","价格":"13.8","餐盒数量":"1","餐盒价格":"1","最小购买量":"1","折扣价格":"","折扣限购":""},{"店铺id":"9411146","分类名称":"鲜奶系列","商品名称":"鲜奶红豆","价格":"13.8","餐盒数量":"1","餐盒价格":"1","最小购买量":"1","折扣价格":"","折扣限购":""},{"店铺id":"9411146","分类名称":"鲜奶系列","商品名称":"木瓜鲜奶","价格":"13.8","餐盒数量":"1","餐盒价格":"1","最小购买量":"1","折扣价格":"","折扣限购":""},{"店铺id":"9411146","分类名称":"鲜奶系列","商品名称":"鲜奶香芋","价格":"13.8","餐盒数量":"1","餐盒价格":"1","最小购买量":"1","折扣价格":"","折扣限购":""},{"店铺id":"9411146","分类名称":"甜糯汤圆","商品名称":"汤圆绿豆沙","价格":"13.8","餐盒数量":"1","餐盒价格":"1","最小购买量":"1","折扣价格":"9.9","折扣限购":""},{"店铺id":"9411146","分类名称":"甜糯汤圆","商品名称":"椰奶汤圆","价格":"13.8","餐盒数量":"1","餐盒价格":"1","最小购买量":"1","折扣价格":"10.9","折扣限购":""},{"店铺id":"9411146","分类名称":"甜糯汤圆","商品名称":"汤圆椰汁西米露","价格":"13.8","餐盒数量":"1","餐盒价格":"1","最小购买量":"1","折扣价格":"10.9","折扣限购":""},{"店铺id":"9411146","分类名称":"甜糯汤圆","商品名称":"汤圆红豆沙","价格":"13.8","餐盒数量":"1","餐盒价格":"1","最小购买量":"1","折扣价格":"9.9","折扣限购":""},{"店铺id":"9411146","分类名称":"双皮奶类","商品名称":"莲子双皮奶","价格":"13.8","餐盒数量":"1","餐盒价格":"1","最小购买量":"1","折扣价格":"","折扣限购":""},{"店铺id":"9411146","分类名称":"双皮奶类","商品名称":"红豆双皮奶","价格":"13.8","餐盒数量":"1","餐盒价格":"1","最小购买量":"1","折扣价格":"","折扣限购":""},{"店铺id":"9411146","分类名称":"双皮奶类","商品名称":"芋圆双皮奶","价格":"13.8","餐盒数量":"1","餐盒价格":"1","最小购买量":"1","折扣价格":"","折扣限购":""},{"店铺id":"9411146","分类名称":"双皮奶类","商品名称":"芒果双皮奶","价格":"13.8","餐盒数量":"1","餐盒价格":"1","最小购买量":"1","折扣价格":"","折扣限购":""},{"店铺id":"9411146","分类名称":"双皮奶类","商品名称":"奥利奥双皮奶【新品推荐】","价格":"13.8","餐盒数量":"1","餐盒价格":"1","最小购买量":"1","折扣价格":"9.9","折扣限购":""},{"店铺id":"9411146","分类名称":"风味小吃","商品名称":"客家薯饼【2个】","价格":"13.8","餐盒数量":"1","餐盒价格":"1","最小购买量":"1","折扣价格":"","折扣限购":""},{"店铺id":"9411146","分类名称":"风味小吃","商品名称":"上校鸡块(5块)","价格":"13.8","餐盒数量":"1","餐盒价格":"1","最小购买量":"1","折扣价格":"","折扣限购":""},{"店铺id":"9411146","分类名称":"风味小吃","商品名称":"潮汕牛筋丸【5个】","价格":"13.8","餐盒数量":"1","餐盒价格":"1","最小购买量":"1","折扣价格":"","折扣限购":""},{"店铺id":"9411146","分类名称":"风味小吃","商品名称":"泰香虾饼【2个】","价格":"13.8","餐盒数量":"1","餐盒价格":"1","最小购买量":"1","折扣价格":"","折扣限购":""},{"店铺id":"9411146","分类名称":"风味小吃","商品名称":"炸牛奶【3个】","价格":"13.8","餐盒数量":"1","餐盒价格":"1","最小购买量":"1","折扣价格":"","折扣限购":""},{"店铺id":"9411146","分类名称":"风味小吃","商品名称":"川香鸡柳【2根】","价格":"13.8","餐盒数量":"1","餐盒价格":"1","最小购买量":"1","折扣价格":"","折扣限购":""},{"店铺id":"9411146","分类名称":"风味小吃","商品名称":"深海墨鱼丸【4个】","价格":"13.8","餐盒数量":"1","餐盒价格":"1","最小购买量":"1","折扣价格":"","折扣限购":""},{"店铺id":"9411146","分类名称":"风味小吃","商品名称":"Q弹年糕(10条装)","价格":"13.8","餐盒数量":"1","餐盒价格":"1","最小购买量":"1","折扣价格":"","折扣限购":""},{"店铺id":"9411146","分类名称":"风味小吃","商品名称":"炸薯条","价格":"13.8","餐盒数量":"1","餐盒价格":"1","最小购买量":"1","折扣价格":"","折扣限购":""},{"店铺id":"9411146","分类名称":"风味小吃","商品名称":"骨肉相连【3串】","价格":"13.8","餐盒数量":"1","餐盒价格":"1","最小购买量":"1","折扣价格":"","折扣限购":""},{"店铺id":"9411146","分类名称":"风味小吃","商品名称":"肉松章鱼小丸子(4个)","价格":"13.8","餐盒数量":"1","餐盒价格":"1","最小购买量":"1","折扣价格":"","折扣限购":""},{"店铺id":"9411146","分类名称":"风味小吃","商品名称":"咖喱鱼丸【6个】","价格":"13.8","餐盒数量":"1","餐盒价格":"1","最小购买量":"1","折扣价格":"","折扣限购":""},{"店铺id":"9411146","分类名称":"风味小吃","商品名称":"炸双皮奶【3个】","价格":"13.8","餐盒数量":"1","餐盒价格":"1","最小购买量":"1","折扣价格":"","折扣限购":""},{"店铺id":"9411146","分类名称":"风味小吃","商品名称":"南瓜饼(5个)","价格":"13.8","餐盒数量":"1","餐盒价格":"1","最小购买量":"1","折扣价格":"8.8","折扣限购":""},{"店铺id":"9411146","分类名称":"风味小吃","商品名称":"香芋地瓜丸【6个】","价格":"13.8","餐盒数量":"1","餐盒价格":"1","最小购买量":"1","折扣价格":"","折扣限购":""},{"店铺id":"9411146","分类名称":"风味小吃","商品名称":"爆浆鸡排","价格":"13.8","餐盒数量":"1","餐盒价格":"1","最小购买量":"1","折扣价格":"8.8","折扣限购":""},{"店铺id":"9411146","分类名称":"风味小吃","商品名称":"台湾盐酥鸡","价格":"13.8","餐盒数量":"1","餐盒价格":"1","最小购买量":"1","折扣价格":"","折扣限购":""},{"店铺id":"9411146","分类名称":"韩式烤冷面","商品名称":"香葱烤冷面","价格":"13.8","餐盒数量":"1","餐盒价格":"1","最小购买量":"1","折扣价格":"","折扣限购":""},{"店铺id":"9411146","分类名称":"风味小吃","商品名称":"日式章鱼小丸子【4个】","价格":"13.8","餐盒数量":"1","餐盒价格":"1","最小购买量":"1","折扣价格":"","折扣限购":""},{"店铺id":"9411146","分类名称":"韩式烤冷面","商品名称":"肉松烤冷面【酸甜味】","价格":"13.8","餐盒数量":"1","餐盒价格":"1","最小购买量":"1","折扣价格":"","折扣限购":""},{"店铺id":"9411146","分类名称":"韩式烤冷面","商品名称":"培根烤冷面","价格":"13.8","餐盒数量":"1","餐盒价格":"1","最小购买量":"1","折扣价格":"","折扣限购":""},{"店铺id":"9411146","分类名称":"风味小吃","商品名称":"正宗重庆酸辣粉【麻辣酸爽】","价格":"13.8","餐盒数量":"1","餐盒价格":"1","最小购买量":"1","折扣价格":"","折扣限购":""},{"店铺id":"9411146","分类名称":"韩式烤冷面","商品名称":"双蛋烤冷面","价格":"13.8","餐盒数量":"1","餐盒价格":"1","最小购买量":"1","折扣价格":"","折扣限购":""},{"店铺id":"9411146","分类名称":"肉馅锅盔","商品名称":"招牌梅干菜锅盔(推荐)","价格":"13.8","餐盒数量":"1","餐盒价格":"1","最小购买量":"1","折扣价格":"8.8","折扣限购":""},{"店铺id":"9411146","分类名称":"肉馅锅盔","商品名称":"鲜肉锅盔(鲜香)","价格":"13.8","餐盒数量":"1","餐盒价格":"1","最小购买量":"1","折扣价格":"","折扣限购":""},{"店铺id":"9411146","分类名称":"养颜桃胶","商品名称":"桃胶绿豆沙","价格":"13.8","餐盒数量":"1","餐盒价格":"1","最小购买量":"1","折扣价格":"","折扣限购":""},{"店铺id":"9411146","分类名称":"养颜桃胶","商品名称":"木瓜桃胶椰汁西米露","价格":"13.8","餐盒数量":"1","餐盒价格":"1","最小购买量":"1","折扣价格":"","折扣限购":""},{"店铺id":"9411146","分类名称":"养颜桃胶","商品名称":"雪耳桃胶羹","价格":"13.8","餐盒数量":"1","餐盒价格":"1","最小购买量":"1","折扣价格":"","折扣限购":""},{"店铺id":"9411146","分类名称":"养颜桃胶","商品名称":"桃胶椰汁西米露","价格":"13.8","餐盒数量":"1","餐盒价格":"1","最小购买量":"1","折扣价格":"","折扣限购":""},{"店铺id":"9411146","分类名称":"养颜桃胶","商品名称":"木瓜鲜奶炖桃胶【推荐！！】","价格":"13.8","餐盒数量":"1","餐盒价格":"1","最小购买量":"1","折扣价格":"","折扣限购":""},{"店铺id":"9411146","分类名称":"养颜桃胶","商品名称":"芋圆桃胶椰汁西米露","价格":"13.8","餐盒数量":"1","餐盒价格":"1","最小购买量":"1","折扣价格":"","折扣限购":""},{"店铺id":"9411146","分类名称":"台湾手抓饼","商品名称":"台湾手抓饼(双拼)","价格":"13.8","餐盒数量":"1","餐盒价格":"1","最小购买量":"1","折扣价格":"","折扣限购":""},{"店铺id":"9411146","分类名称":"台湾手抓饼","商品名称":"台湾手抓饼(三拼)","价格":"13.8","餐盒数量":"1","餐盒价格":"1","最小购买量":"1","折扣价格":"","折扣限购":""},{"店铺id":"9411146","分类名称":"台湾手抓饼","商品名称":"豪华台湾手抓饼(三拼)$","价格":"13.8","餐盒数量":"1","餐盒价格":"1","最小购买量":"1","折扣价格":"8.8","折扣限购":""},{"店铺id":"9411146","分类名称":"嫩滑仙草","商品名称":"椰奶烧仙草","价格":"13.8","餐盒数量":"1","餐盒价格":"1","最小购买量":"1","折扣价格":"","折扣限购":""},{"店铺id":"9411146","分类名称":"嫩滑仙草","商品名称":"酸奶烧仙草","价格":"13.8","餐盒数量":"1","餐盒价格":"1","最小购买量":"1","折扣价格":"","折扣限购":""},{"店铺id":"9411146","分类名称":"嫩滑仙草","商品名称":"芋圆奶茶烧仙草【Q弹有料】","价格":"13.8","餐盒数量":"1","餐盒价格":"1","最小购买量":"1","折扣价格":"","折扣限购":""},{"店铺id":"9411146","分类名称":"嫩滑仙草","商品名称":"芋圆酸奶烧仙草","价格":"13.8","餐盒数量":"1","餐盒价格":"1","最小购买量":"1","折扣价格":"","折扣限购":""},{"店铺id":"9411146","分类名称":"嫩滑仙草","商品名称":"招牌烧仙草【爆品！料超多！】","价格":"13.8","餐盒数量":"1","餐盒价格":"1","最小购买量":"1","折扣价格":"","折扣限购":""},{"店铺id":"9411146","分类名称":"手工芋圆","商品名称":"芋圆烧仙草【Q弹有料】","价格":"13.8","餐盒数量":"1","餐盒价格":"1","最小购买量":"1","折扣价格":"","折扣限购":""},{"店铺id":"9411146","分类名称":"手工芋圆","商品名称":"芋圆2号【红豆+西米+芋圆+地瓜】","价格":"13.8","餐盒数量":"1","餐盒价格":"1","最小购买量":"1","折扣价格":"","折扣限购":""},{"店铺id":"9411146","分类名称":"手工芋圆","商品名称":"芋圆红豆香芋","价格":"13.8","餐盒数量":"1","餐盒价格":"1","最小购买量":"1","折扣价格":"","折扣限购":""},{"店铺id":"9411146","分类名称":"手工芋圆","商品名称":"招牌芋圆【店长推荐】","价格":"13.8","餐盒数量":"1","餐盒价格":"1","最小购买量":"1","折扣价格":"8.9","折扣限购":""},{"店铺id":"9808200","分类名称":"肉馅锅盔","商品名称":"招牌鲜肉锅盔(鲜香)","价格":"13.8","餐盒数量":"1","餐盒价格":"1","最小购买量":"1","折扣价格":"","折扣限购":""},{"店铺id":"9808200","分类名称":"风味小吃","商品名称":"牛筋丸(5个)","价格":"13.8","餐盒数量":"1","餐盒价格":"1","最小购买量":"1","折扣价格":"","折扣限购":""},{"店铺id":"9808200","分类名称":"风味小吃","商品名称":"上校鸡块(5块)","价格":"13.8","餐盒数量":"1","餐盒价格":"1","最小购买量":"1","折扣价格":"","折扣限购":""},{"店铺id":"9808200","分类名称":"风味小吃","商品名称":"香芋地瓜丸【6个】","价格":"13.8","餐盒数量":"1","餐盒价格":"1","最小购买量":"1","折扣价格":"","折扣限购":""},{"店铺id":"9808200","分类名称":"风味小吃","商品名称":"咖喱鱼丸【6个】","价格":"13.8","餐盒数量":"1","餐盒价格":"1","最小购买量":"1","折扣价格":"","折扣限购":""},{"店铺id":"9808200","分类名称":"台湾手抓饼","商品名称":"台湾手抓饼(双拼)","价格":"13.8","餐盒数量":"1","餐盒价格":"1","最小购买量":"1","折扣价格":"","折扣限购":""},{"店铺id":"9808200","分类名称":"风味小吃","商品名称":"骨肉相连(3串)","价格":"13.8","餐盒数量":"1","餐盒价格":"1","最小购买量":"1","折扣价格":"","折扣限购":""},{"店铺id":"9808200","分类名称":"台湾手抓饼","商品名称":"台湾手抓饼(三拼)","价格":"13.8","餐盒数量":"1","餐盒价格":"1","最小购买量":"1","折扣价格":"","折扣限购":""},{"店铺id":"9808200","分类名称":"风味小吃","商品名称":"台湾盐酥鸡","价格":"13.8","餐盒数量":"1","餐盒价格":"1","最小购买量":"1","折扣价格":"","折扣限购":""},{"店铺id":"9808200","分类名称":"风味小吃","商品名称":"日式章鱼小丸子【4个】","价格":"13.8","餐盒数量":"1","餐盒价格":"1","最小购买量":"1","折扣价格":"","折扣限购":""},{"店铺id":"9808200","分类名称":"风味小吃","商品名称":"正宗重庆酸辣粉【麻辣酸爽】","价格":"13.8","餐盒数量":"1","餐盒价格":"1","最小购买量":"1","折扣价格":"","折扣限购":""},{"店铺id":"9808200","分类名称":"精选奶茶","商品名称":"黑钻奶茶","价格":"13.8","餐盒数量":"1","餐盒价格":"1","最小购买量":"1","折扣价格":"","折扣限购":""},{"店铺id":"9808200","分类名称":"精选奶茶","商品名称":"冲绳黑钻霸","价格":"13.8","餐盒数量":"1","餐盒价格":"1","最小购买量":"1","折扣价格":"","折扣限购":""},{"店铺id":"9808200","分类名称":"精选奶茶","商品名称":"双拼奶茶","价格":"13.8","餐盒数量":"1","餐盒价格":"1","最小购买量":"1","折扣价格":"","折扣限购":""},{"店铺id":"9808200","分类名称":"精选奶茶","商品名称":"金时布丁抹茶","价格":"13.8","餐盒数量":"1","餐盒价格":"1","最小购买量":"1","折扣价格":"","折扣限购":""},{"店铺id":"9808200","分类名称":"精选奶茶","商品名称":"香米阿华田","价格":"13.8","餐盒数量":"1","餐盒价格":"1","最小购买量":"1","折扣价格":"","折扣限购":""},{"店铺id":"9808200","分类名称":"精选奶茶","商品名称":"茶香奶绿","价格":"13.8","餐盒数量":"1","餐盒价格":"1","最小购买量":"1","折扣价格":"","折扣限购":""},{"店铺id":"9808200","分类名称":"精选奶茶","商品名称":"北海布丁秀","价格":"13.8","餐盒数量":"1","餐盒价格":"1","最小购买量":"1","折扣价格":"","折扣限购":""},{"店铺id":"9808200","分类名称":"精选奶茶","商品名称":"碳烧黑糖冻奶茶","价格":"13.8","餐盒数量":"1","餐盒价格":"1","最小购买量":"1","折扣价格":"","折扣限购":""},{"店铺id":"9808200","分类名称":"精选奶茶","商品名称":"香米椰奶红豆","价格":"13.8","餐盒数量":"1","餐盒价格":"1","最小购买量":"1","折扣价格":"","折扣限购":""},{"店铺id":"9808200","分类名称":"精选奶茶","商品名称":"仙草冻奶茶","价格":"13.8","餐盒数量":"1","餐盒价格":"1","最小购买量":"1","折扣价格":"","折扣限购":""},{"店铺id":"9808200","分类名称":"精选奶茶","商品名称":"金钻奶茶","价格":"13.8","餐盒数量":"1","餐盒价格":"1","最小购买量":"1","折扣价格":"","折扣限购":""},{"店铺id":"9808200","分类名称":"精选奶茶","商品名称":"布丁奶茶","价格":"13.8","餐盒数量":"1","餐盒价格":"1","最小购买量":"1","折扣价格":"","折扣限购":""},{"店铺id":"9808200","分类名称":"精选奶茶","商品名称":"奥利奥奶茶","价格":"13.8","餐盒数量":"1","餐盒价格":"1","最小购买量":"1","折扣价格":"","折扣限购":""},{"店铺id":"9808200","分类名称":"精选奶茶","商品名称":"香米抹茶红豆","价格":"13.8","餐盒数量":"1","餐盒价格":"1","最小购买量":"1","折扣价格":"","折扣限购":""},{"店铺id":"9808200","分类名称":"精选奶茶","商品名称":"格雷三兄弟","价格":"13.8","餐盒数量":"1","餐盒价格":"1","最小购买量":"1","折扣价格":"","折扣限购":""},{"店铺id":"9808200","分类名称":"精选奶茶","商品名称":"原味奶茶(纯奶茶)","价格":"13.8","餐盒数量":"1","餐盒价格":"1","最小购买量":"1","折扣价格":"","折扣限购":""},{"店铺id":"9808200","分类名称":"精选奶茶","商品名称":"红豆布丁奶茶","价格":"13.8","餐盒数量":"1","餐盒价格":"1","最小购买量":"1","折扣价格":"","折扣限购":""},{"店铺id":"9808200","分类名称":"精选奶茶","商品名称":"椰果奶茶","价格":"13.8","餐盒数量":"1","餐盒价格":"1","最小购买量":"1","折扣价格":"","折扣限购":""},{"店铺id":"9808200","分类名称":"精选奶茶","商品名称":"波霸珍珠奶茶","价格":"13.8","餐盒数量":"1","餐盒价格":"1","最小购买量":"1","折扣价格":"","折扣限购":""},{"店铺id":"9808200","分类名称":"精选奶茶","商品名称":"招牌烧仙草奶茶(料多好味道)","价格":"13.8","餐盒数量":"1","餐盒价格":"1","最小购买量":"1","折扣价格":"","折扣限购":""},{"店铺id":"9808200","分类名称":"精选奶茶","商品名称":"DIY霸气珍珠奶茶","价格":"13.8","餐盒数量":"1","餐盒价格":"1","最小购买量":"1","折扣价格":"","折扣限购":""},{"店铺id":"9808200","分类名称":"韩式烤冷面","商品名称":"肉松烤冷面","价格":"13.8","餐盒数量":"1","餐盒价格":"1","最小购买量":"1","折扣价格":"","折扣限购":""},{"店铺id":"9808200","分类名称":"韩式烤冷面","商品名称":"双蛋烤冷面","价格":"13.8","餐盒数量":"1","餐盒价格":"1","最小购买量":"1","折扣价格":"","折扣限购":""},{"店铺id":"9808200","分类名称":"韩式烤冷面","商品名称":"培根烤冷面","价格":"13.8","餐盒数量":"1","餐盒价格":"1","最小购买量":"1","折扣价格":"","折扣限购":""},{"店铺id":"8195835","分类名称":"甜糯汤圆","商品名称":"汤圆绿豆沙","价格":"13.8","餐盒数量":"1","餐盒价格":"1","最小购买量":"1","折扣价格":"9.9","折扣限购":""},{"店铺id":"8195835","分类名称":"甜糯汤圆","商品名称":"椰奶汤圆","价格":"13.8","餐盒数量":"1","餐盒价格":"1","最小购买量":"1","折扣价格":"10.9","折扣限购":""},{"店铺id":"8195835","分类名称":"甜糯汤圆","商品名称":"汤圆椰汁西米露","价格":"13.8","餐盒数量":"1","餐盒价格":"1","最小购买量":"1","折扣价格":"10.9","折扣限购":""},{"店铺id":"8195835","分类名称":"甜糯汤圆","商品名称":"汤圆红豆沙","价格":"13.8","餐盒数量":"1","餐盒价格":"1","最小购买量":"1","折扣价格":"9.9","折扣限购":""},{"店铺id":"8195835","分类名称":"甜糯汤圆","商品名称":"清水汤圆【8颗】$","价格":"13.8","餐盒数量":"1","餐盒价格":"1","最小购买量":"1","折扣价格":"8.8","折扣限购":""},{"店铺id":"8195835","分类名称":"必抢折扣","商品名称":"草莓脏脏茶(外卖不挂杯属于正常现象)$","价格":"13.8","餐盒数量":"1","餐盒价格":"1.9","最小购买量":"1","折扣价格":"9.9","折扣限购":""},{"店铺id":"8195835","分类名称":"必抢折扣","商品名称":"相思红豆奶茶(必抢)$","价格":"13.8","餐盒数量":"1","餐盒价格":"1.99","最小购买量":"1","折扣价格":"8.8","折扣限购":""},{"店铺id":"8195835","分类名称":"必抢折扣","商品名称":"芋泥波波茶$","价格":"13.8","餐盒数量":"1","餐盒价格":"1.9","最小购买量":"1","折扣价格":"8.8","折扣限购":""},{"店铺id":"8195835","分类名称":"必抢折扣","商品名称":"波霸珍珠奶茶【大杯】$","价格":"13.8","餐盒数量":"1","餐盒价格":"1.9","最小购买量":"1","折扣价格":"8.8","折扣限购":""},{"店铺id":"8195835","分类名称":"必抢折扣","商品名称":"血糯米奶茶(新品必抢)$","价格":"13.8","餐盒数量":"1","餐盒价格":"1.9","最小购买量":"1","折扣价格":"8.8","折扣限购":""},{"店铺id":"8195835","分类名称":"必抢折扣","商品名称":"芝士葡萄【大杯】$","价格":"13.8","餐盒数量":"1","餐盒价格":"1.9","最小购买量":"1","折扣价格":"11.8","折扣限购":""},{"店铺id":"8195835","分类名称":"必抢折扣","商品名称":"鲜杯桃桃$","价格":"13.8","餐盒数量":"1","餐盒价格":"1.9","最小购买量":"1","折扣价格":"8.8","折扣限购":""},{"店铺id":"8195835","分类名称":"精选奶茶","商品名称":"北海布丁秀","价格":"13.8","餐盒数量":"1","餐盒价格":"1","最小购买量":"1","折扣价格":"","折扣限购":""},{"店铺id":"8195835","分类名称":"必抢折扣","商品名称":"手打柠檬绿茶(大杯)$","价格":"13.8","餐盒数量":"1","餐盒价格":"1.9","最小购买量":"1","折扣价格":"8.8","折扣限购":""},{"店铺id":"8195835","分类名称":"精选奶茶","商品名称":"冲绳黑钻霸","价格":"13.8","餐盒数量":"1","餐盒价格":"1","最小购买量":"1","折扣价格":"","折扣限购":""},{"店铺id":"8195835","分类名称":"必抢折扣","商品名称":"招牌芋圆奶茶$(大杯)","价格":"13.8","餐盒数量":"1","餐盒价格":"1","最小购买量":"1","折扣价格":"9.9","折扣限购":""},{"店铺id":"8195835","分类名称":"必抢折扣","商品名称":"招牌烧仙草(墙裂推荐！！)$","价格":"13.8","餐盒数量":"1","餐盒价格":"1.98","最小购买量":"1","折扣价格":"7.8","折扣限购":""},{"店铺id":"8195835","分类名称":"精选奶茶","商品名称":"仙草冻奶茶","价格":"13.8","餐盒数量":"1","餐盒价格":"1","最小购买量":"1","折扣价格":"","折扣限购":""},{"店铺id":"8195835","分类名称":"必抢折扣","商品名称":"手打柠檬红茶(大杯)$","价格":"13.8","餐盒数量":"1","餐盒价格":"1","最小购买量":"1","折扣价格":"8.8","折扣限购":""},{"店铺id":"8195835","分类名称":"精选奶茶","商品名称":"碳烧黑糖冻奶茶","价格":"13.8","餐盒数量":"1","餐盒价格":"1","最小购买量":"1","折扣价格":"","折扣限购":""},{"店铺id":"8195835","分类名称":"必抢折扣","商品名称":"鲜百香双响炮(大杯)$","价格":"13.8","餐盒数量":"1","餐盒价格":"1","最小购买量":"1","折扣价格":"8.8","折扣限购":""},{"店铺id":"8195835","分类名称":"精选奶茶","商品名称":"黑钻奶茶","价格":"13.8","餐盒数量":"1","餐盒价格":"1","最小购买量":"1","折扣价格":"","折扣限购":""},{"店铺id":"8195835","分类名称":"精选奶茶","商品名称":"香米椰奶红豆","价格":"13.8","餐盒数量":"1","餐盒价格":"1","最小购买量":"1","折扣价格":"","折扣限购":""},{"店铺id":"8195835","分类名称":"精选奶茶","商品名称":"香米阿华田","价格":"13.8","餐盒数量":"1","餐盒价格":"1","最小购买量":"1","折扣价格":"","折扣限购":""},{"店铺id":"8195835","分类名称":"精选奶茶","商品名称":"茶香奶绿","价格":"13.8","餐盒数量":"1","餐盒价格":"1","最小购买量":"1","折扣价格":"","折扣限购":""},{"店铺id":"8195835","分类名称":"精选奶茶","商品名称":"金时布丁抹茶","价格":"13.8","餐盒数量":"1","餐盒价格":"1","最小购买量":"1","折扣价格":"","折扣限购":""},{"店铺id":"8195835","分类名称":"精选奶茶","商品名称":"布丁奶茶","价格":"13.8","餐盒数量":"1","餐盒价格":"1","最小购买量":"1","折扣价格":"","折扣限购":""},{"店铺id":"8195835","分类名称":"精选奶茶","商品名称":"香米抹茶红豆","价格":"13.8","餐盒数量":"1","餐盒价格":"1","最小购买量":"1","折扣价格":"","折扣限购":""},{"店铺id":"8195835","分类名称":"必抢折扣","商品名称":"草莓优酪多(大杯)$","价格":"13.8","餐盒数量":"1","餐盒价格":"1.9","最小购买量":"1","折扣价格":"11.8","折扣限购":""},{"店铺id":"8195835","分类名称":"精选奶茶","商品名称":"奥利奥奶茶","价格":"13.8","餐盒数量":"1","餐盒价格":"1","最小购买量":"1","折扣价格":"","折扣限购":""},{"店铺id":"8195835","分类名称":"精选奶茶","商品名称":"金钻奶茶","价格":"13.8","餐盒数量":"1","餐盒价格":"1","最小购买量":"1","折扣价格":"","折扣限购":""},{"店铺id":"8195835","分类名称":"精选奶茶","商品名称":"双拼奶茶","价格":"13.8","餐盒数量":"1","餐盒价格":"1","最小购买量":"1","折扣价格":"","折扣限购":""},{"店铺id":"8195835","分类名称":"精选奶茶","商品名称":"红豆布丁奶茶","价格":"13.8","餐盒数量":"1","餐盒价格":"1","最小购买量":"1","折扣价格":"","折扣限购":""},{"店铺id":"8195835","分类名称":"精选奶茶","商品名称":"椰果奶茶","价格":"13.8","餐盒数量":"1","餐盒价格":"1","最小购买量":"1","折扣价格":"","折扣限购":""},{"店铺id":"8195835","分类名称":"精选奶茶","商品名称":"格雷三兄弟","价格":"13.8","餐盒数量":"1","餐盒价格":"1","最小购买量":"1","折扣价格":"","折扣限购":""},{"店铺id":"8195835","分类名称":"必抢折扣","商品名称":"芒果鲜果茶(大杯)$","价格":"13.8","餐盒数量":"1","餐盒价格":"1.9","最小购买量":"1","折扣价格":"8.99","折扣限购":""},{"店铺id":"8195835","分类名称":"精选奶茶","商品名称":"血糯米奶茶(大杯)","价格":"13.8","餐盒数量":"1","餐盒价格":"1","最小购买量":"1","折扣价格":"","折扣限购":""},{"店铺id":"8195835","分类名称":"精选奶茶","商品名称":"原味奶茶(纯奶茶)","价格":"13.8","餐盒数量":"1","餐盒价格":"1","最小购买量":"1","折扣价格":"","折扣限购":""},{"店铺id":"8195835","分类名称":"精选奶茶","商品名称":"波霸珍珠奶茶","价格":"13.8","餐盒数量":"1","餐盒价格":"1","最小购买量":"1","折扣价格":"","折扣限购":""},{"店铺id":"8195835","分类名称":"精选奶茶","商品名称":"招牌烧仙草(料多好味道)","价格":"13.8","餐盒数量":"1","餐盒价格":"1","最小购买量":"1","折扣价格":"","折扣限购":""},{"店铺id":"8195835","分类名称":"必抢折扣","商品名称":"熊猫果茶(推荐)$","价格":"13.8","餐盒数量":"1","餐盒价格":"1","最小购买量":"1","折扣价格":"11.8","折扣限购":""},{"店铺id":"8195835","分类名称":"韩式烤冷面","商品名称":"香葱烤冷面","价格":"13.8","餐盒数量":"1","餐盒价格":"1","最小购买量":"1","折扣价格":"","折扣限购":""},{"店铺id":"8195835","分类名称":"风味小吃","商品名称":"香芋地瓜丸【6个】","价格":"13.8","餐盒数量":"1","餐盒价格":"1","最小购买量":"1","折扣价格":"","折扣限购":""},{"店铺id":"8195835","分类名称":"韩式烤冷面","商品名称":"肉松烤冷面","价格":"13.8","餐盒数量":"1","餐盒价格":"1","最小购买量":"1","折扣价格":"","折扣限购":""},{"店铺id":"8195835","分类名称":"风味小吃","商品名称":"炸墨鱼丸【4个】","价格":"13.8","餐盒数量":"1","餐盒价格":"1","最小购买量":"1","折扣价格":"","折扣限购":""},{"店铺id":"8195835","分类名称":"韩式烤冷面","商品名称":"双蛋烤冷面","价格":"13.8","餐盒数量":"1","餐盒价格":"1","最小购买量":"1","折扣价格":"","折扣限购":""},{"店铺id":"8195835","分类名称":"风味小吃","商品名称":"上校鸡块(5块)","价格":"13.8","餐盒数量":"1","餐盒价格":"1","最小购买量":"1","折扣价格":"","折扣限购":""},{"店铺id":"8195835","分类名称":"韩式烤冷面","商品名称":"培根烤冷面","价格":"13.8","餐盒数量":"1","餐盒价格":"1","最小购买量":"1","折扣价格":"","折扣限购":""},{"店铺id":"8195835","分类名称":"风味小吃","商品名称":"咖喱鱼丸【6个】","价格":"13.8","餐盒数量":"1","餐盒价格":"1","最小购买量":"1","折扣价格":"","折扣限购":""},{"店铺id":"8195835","分类名称":"风味小吃","商品名称":"牛筋丸(5个)","价格":"13.8","餐盒数量":"1","餐盒价格":"1","最小购买量":"1","折扣价格":"","折扣限购":""},{"店铺id":"8195835","分类名称":"风味小吃","商品名称":"骨肉相连(3串)","价格":"13.8","餐盒数量":"1","餐盒价格":"1","最小购买量":"1","折扣价格":"","折扣限购":""},{"店铺id":"8195835","分类名称":"台湾手抓饼","商品名称":"台湾手抓饼(双拼)","价格":"13.8","餐盒数量":"1","餐盒价格":"1","最小购买量":"1","折扣价格":"","折扣限购":""},{"店铺id":"8195835","分类名称":"风味小吃","商品名称":"炸牛奶【3个】","价格":"13.8","餐盒数量":"1","餐盒价格":"1","最小购买量":"1","折扣价格":"","折扣限购":""},{"店铺id":"8195835","分类名称":"台湾手抓饼","商品名称":"豪华台湾手抓饼(三拼)$","价格":"13.8","餐盒数量":"1","餐盒价格":"1.98","最小购买量":"1","折扣价格":"7.8","折扣限购":""},{"店铺id":"8195835","分类名称":"风味小吃","商品名称":"日式章鱼小丸子【4个】","价格":"13.8","餐盒数量":"1","餐盒价格":"1","最小购买量":"1","折扣价格":"","折扣限购":""},{"店铺id":"8195835","分类名称":"❣️❣️❣️福利社","商品名称":"点亮右上丨法式焦糖烤布蕾（粉丝专享，交个朋友）","价格":"13.8","餐盒数量":"1","餐盒价格":"1","最小购买量":"1","折扣价格":"3.99","折扣限购":"1"},{"店铺id":"","分类名称":"","商品名称":"","价格":"","餐盒数量":"","餐盒价格":"","最小购买量":"","折扣价格":"","折扣限购":""},{"店铺id":"","分类名称":"","商品名称":"","价格":"","餐盒数量":"","餐盒价格":"","最小购买量":"","折扣价格":"","折扣限购":""},{"店铺id":"","分类名称":"","商品名称":"","价格":"","餐盒数量":"","餐盒价格":"","最小购买量":"","折扣价格":"","折扣限购":""},{"店铺id":"","分类名称":"","商品名称":"","价格":"","餐盒数量":"","餐盒价格":"","最小购买量":"","折扣价格":"","折扣限购":""},{"店铺id":"","分类名称":"","商品名称":"","价格":"","餐盒数量":"","餐盒价格":"","最小购买量":"","折扣价格":"","折扣限购":""},{"店铺id":"","分类名称":"","商品名称":"","价格":"","餐盒数量":"","餐盒价格":"","最小购买量":"","折扣价格":"","折扣限购":""},{"店铺id":"","分类名称":"","商品名称":"","价格":"","餐盒数量":"","餐盒价格":"","最小购买量":"","折扣价格":"","折扣限购":""},{"店铺id":"","分类名称":"","商品名称":"","价格":"","餐盒数量":"","餐盒价格":"","最小购买量":"","折扣价格":"","折扣限购":""},{"店铺id":"","分类名称":"","商品名称":"","价格":"","餐盒数量":"","餐盒价格":"","最小购买量":"","折扣价格":"","折扣限购":""},{"店铺id":"","分类名称":"","商品名称":"","价格":"","餐盒数量":"","餐盒价格":"","最小购买量":"","折扣价格":"","折扣限购":""},{"店铺id":"","分类名称":"","商品名称":"","价格":"","餐盒数量":"","餐盒价格":"","最小购买量":"","折扣价格":"","折扣限购":""},{"店铺id":"","分类名称":"","商品名称":"","价格":"","餐盒数量":"","餐盒价格":"","最小购买量":"","折扣价格":"","折扣限购":""},{"店铺id":"","分类名称":"","商品名称":"","价格":"","餐盒数量":"","餐盒价格":"","最小购买量":"","折扣价格":"","折扣限购":""},{"店铺id":"","分类名称":"","商品名称":"","价格":"","餐盒数量":"","餐盒价格":"","最小购买量":"","折扣价格":"","折扣限购":""},{"店铺id":"","分类名称":"","商品名称":"","价格":"","餐盒数量":"","餐盒价格":"","最小购买量":"","折扣价格":"","折扣限购":""},{"店铺id":"","分类名称":"","商品名称":"","价格":"","餐盒数量":"","餐盒价格":"","最小购买量":"","折扣价格":"","折扣限购":""},{"店铺id":"","分类名称":"","商品名称":"","价格":"","餐盒数量":"","餐盒价格":"","最小购买量":"","折扣价格":"","折扣限购":""},{"店铺id":"","分类名称":"","商品名称":"","价格":"","餐盒数量":"","餐盒价格":"","最小购买量":"","折扣价格":"","折扣限购":""},{"店铺id":"","分类名称":"","商品名称":"","价格":"","餐盒数量":"","餐盒价格":"","最小购买量":"","折扣价格":"","折扣限购":""},{"店铺id":"","分类名称":"","商品名称":"","价格":"","餐盒数量":"","餐盒价格":"","最小购买量":"","折扣价格":"","折扣限购":""},{"店铺id":"","分类名称":"","商品名称":"","价格":"","餐盒数量":"","餐盒价格":"","最小购买量":"","折扣价格":"","折扣限购":""},{"店铺id":"","分类名称":"","商品名称":"","价格":"","餐盒数量":"","餐盒价格":"","最小购买量":"","折扣价格":"","折扣限购":""},{"店铺id":"","分类名称":"","商品名称":"","价格":"","餐盒数量":"","餐盒价格":"","最小购买量":"","折扣价格":"","折扣限购":""},{"店铺id":"","分类名称":"","商品名称":"","价格":"","餐盒数量":"","餐盒价格":"","最小购买量":"","折扣价格":"","折扣限购":""},{"店铺id":"","分类名称":"","商品名称":"","价格":"","餐盒数量":"","餐盒价格":"","最小购买量":"","折扣价格":"","折扣限购":""},{"店铺id":"","分类名称":"","商品名称":"","价格":"","餐盒数量":"","餐盒价格":"","最小购买量":"","折扣价格":"","折扣限购":""},{"店铺id":"","分类名称":"","商品名称":"","价格":"","餐盒数量":"","餐盒价格":"","最小购买量":"","折扣价格":"","折扣限购":""},{"店铺id":"","分类名称":"","商品名称":"","价格":"","餐盒数量":"","餐盒价格":"","最小购买量":"","折扣价格":"","折扣限购":""},{"店铺id":"","分类名称":"","商品名称":"","价格":"","餐盒数量":"","餐盒价格":"","最小购买量":"","折扣价格":"","折扣限购":""},{"店铺id":"","分类名称":"","商品名称":"","价格":"","餐盒数量":"","餐盒价格":"","最小购买量":"","折扣价格":"","折扣限购":""},{"店铺id":"","分类名称":"","商品名称":"","价格":"","餐盒数量":"","餐盒价格":"","最小购买量":"","折扣价格":"","折扣限购":""},{"店铺id":"","分类名称":"","商品名称":"","价格":"","餐盒数量":"","餐盒价格":"","最小购买量":"","折扣价格":"","折扣限购":""},{"店铺id":"","分类名称":"","商品名称":"","价格":"","餐盒数量":"","餐盒价格":"","最小购买量":"","折扣价格":"","折扣限购":""},{"店铺id":"","分类名称":"","商品名称":"","价格":"","餐盒数量":"","餐盒价格":"","最小购买量":"","折扣价格":"","折扣限购":""},{"店铺id":"","分类名称":"","商品名称":"","价格":"","餐盒数量":"","餐盒价格":"","最小购买量":"","折扣价格":"","折扣限购":""},{"店铺id":"","分类名称":"","商品名称":"","价格":"","餐盒数量":"","餐盒价格":"","最小购买量":"","折扣价格":"","折扣限购":""},{"店铺id":"","分类名称":"","商品名称":"","价格":"","餐盒数量":"","餐盒价格":"","最小购买量":"","折扣价格":"","折扣限购":""},{"店铺id":"","分类名称":"","商品名称":"","价格":"","餐盒数量":"","餐盒价格":"","最小购买量":"","折扣价格":"","折扣限购":""},{"店铺id":"","分类名称":"","商品名称":"","价格":"","餐盒数量":"","餐盒价格":"","最小购买量":"","折扣价格":"","折扣限购":""},{"店铺id":"","分类名称":"","商品名称":"","价格":"","餐盒数量":"","餐盒价格":"","最小购买量":"","折扣价格":"","折扣限购":""},{"店铺id":"","分类名称":"","商品名称":"","价格":"","餐盒数量":"","餐盒价格":"","最小购买量":"","折扣价格":"","折扣限购":""},{"店铺id":"","分类名称":"","商品名称":"","价格":"","餐盒数量":"","餐盒价格":"","最小购买量":"","折扣价格":"","折扣限购":""},{"店铺id":"","分类名称":"","商品名称":"","价格":"","餐盒数量":"","餐盒价格":"","最小购买量":"","折扣价格":"","折扣限购":""},{"店铺id":"","分类名称":"","商品名称":"","价格":"","餐盒数量":"","餐盒价格":"","最小购买量":"","折扣价格":"","折扣限购":""},{"店铺id":"","分类名称":"","商品名称":"","价格":"","餐盒数量":"","餐盒价格":"","最小购买量":"","折扣价格":"","折扣限购":""},{"店铺id":"","分类名称":"","商品名称":"","价格":"","餐盒数量":"","餐盒价格":"","最小购买量":"","折扣价格":"","折扣限购":""},{"店铺id":"","分类名称":"","商品名称":"","价格":"","餐盒数量":"","餐盒价格":"","最小购买量":"","折扣价格":"","折扣限购":""},{"店铺id":"","分类名称":"","商品名称":"","价格":"","餐盒数量":"","餐盒价格":"","最小购买量":"","折扣价格":"","折扣限购":""},{"店铺id":"","分类名称":"","商品名称":"","价格":"","餐盒数量":"","餐盒价格":"","最小购买量":"","折扣价格":"","折扣限购":""},{"店铺id":"","分类名称":"","商品名称":"","价格":"","餐盒数量":"","餐盒价格":"","最小购买量":"","折扣价格":"","折扣限购":""},{"店铺id":"","分类名称":"","商品名称":"","价格":"","餐盒数量":"","餐盒价格":"","最小购买量":"","折扣价格":"","折扣限购":""},{"店铺id":"","分类名称":"","商品名称":"","价格":"","餐盒数量":"","餐盒价格":"","最小购买量":"","折扣价格":"","折扣限购":""},{"店铺id":"","分类名称":"","商品名称":"","价格":"","餐盒数量":"","餐盒价格":"","最小购买量":"","折扣价格":"","折扣限购":""},{"店铺id":"","分类名称":"","商品名称":"","价格":"","餐盒数量":"","餐盒价格":"","最小购买量":"","折扣价格":"","折扣限购":""},{"店铺id":"","分类名称":"","商品名称":"","价格":"","餐盒数量":"","餐盒价格":"","最小购买量":"","折扣价格":"","折扣限购":""},{"店铺id":"","分类名称":"","商品名称":"","价格":"","餐盒数量":"","餐盒价格":"","最小购买量":"","折扣价格":"","折扣限购":""},{"店铺id":"","分类名称":"","商品名称":"","价格":"","餐盒数量":"","餐盒价格":"","最小购买量":"","折扣价格":"","折扣限购":""},{"店铺id":"","分类名称":"","商品名称":"","价格":"","餐盒数量":"","餐盒价格":"","最小购买量":"","折扣价格":"","折扣限购":""},{"店铺id":"","分类名称":"","商品名称":"","价格":"","餐盒数量":"","餐盒价格":"","最小购买量":"","折扣价格":"","折扣限购":""},{"店铺id":"","分类名称":"","商品名称":"","价格":"","餐盒数量":"","餐盒价格":"","最小购买量":"","折扣价格":"","折扣限购":""},{"店铺id":"","分类名称":"","商品名称":"","价格":"","餐盒数量":"","餐盒价格":"","最小购买量":"","折扣价格":"","折扣限购":""},{"店铺id":"","分类名称":"","商品名称":"","价格":"","餐盒数量":"","餐盒价格":"","最小购买量":"","折扣价格":"","折扣限购":""},{"店铺id":"","分类名称":"","商品名称":"","价格":"","餐盒数量":"","餐盒价格":"","最小购买量":"","折扣价格":"","折扣限购":""},{"店铺id":"","分类名称":"","商品名称":"","价格":"","餐盒数量":"","餐盒价格":"","最小购买量":"","折扣价格":"","折扣限购":""},{"店铺id":"","分类名称":"","商品名称":"","价格":"","餐盒数量":"","餐盒价格":"","最小购买量":"","折扣价格":"","折扣限购":""},{"店铺id":"","分类名称":"","商品名称":"","价格":"","餐盒数量":"","餐盒价格":"","最小购买量":"","折扣价格":"","折扣限购":""},{"店铺id":"","分类名称":"","商品名称":"","价格":"","餐盒数量":"","餐盒价格":"","最小购买量":"","折扣价格":"","折扣限购":""},{"店铺id":"","分类名称":"","商品名称":"","价格":"","餐盒数量":"","餐盒价格":"","最小购买量":"","折扣价格":"","折扣限购":""},{"店铺id":"","分类名称":"","商品名称":"","价格":"","餐盒数量":"","餐盒价格":"","最小购买量":"","折扣价格":"","折扣限购":""},{"店铺id":"","分类名称":"","商品名称":"","价格":"","餐盒数量":"","餐盒价格":"","最小购买量":"","折扣价格":"","折扣限购":""},{"店铺id":"","分类名称":"","商品名称":"","价格":"","餐盒数量":"","餐盒价格":"","最小购买量":"","折扣价格":"","折扣限购":""},{"店铺id":"","分类名称":"","商品名称":"","价格":"","餐盒数量":"","餐盒价格":"","最小购买量":"","折扣价格":"","折扣限购":""},{"店铺id":"","分类名称":"","商品名称":"","价格":"","餐盒数量":"","餐盒价格":"","最小购买量":"","折扣价格":"","折扣限购":""},{"店铺id":"","分类名称":"","商品名称":"","价格":"","餐盒数量":"","餐盒价格":"","最小购买量":"","折扣价格":"","折扣限购":""},{"店铺id":"","分类名称":"","商品名称":"","价格":"","餐盒数量":"","餐盒价格":"","最小购买量":"","折扣价格":"","折扣限购":""},{"店铺id":"","分类名称":"","商品名称":"","价格":"","餐盒数量":"","餐盒价格":"","最小购买量":"","折扣价格":"","折扣限购":""},{"店铺id":"","分类名称":"","商品名称":"","价格":"","餐盒数量":"","餐盒价格":"","最小购买量":"","折扣价格":"","折扣限购":""},{"店铺id":"","分类名称":"","商品名称":"","价格":"","餐盒数量":"","餐盒价格":"","最小购买量":"","折扣价格":"","折扣限购":""},{"店铺id":"","分类名称":"","商品名称":"","价格":"","餐盒数量":"","餐盒价格":"","最小购买量":"","折扣价格":"","折扣限购":""},{"店铺id":"","分类名称":"","商品名称":"","价格":"","餐盒数量":"","餐盒价格":"","最小购买量":"","折扣价格":"","折扣限购":""},{"店铺id":"","分类名称":"","商品名称":"","价格":"","餐盒数量":"","餐盒价格":"","最小购买量":"","折扣价格":"","折扣限购":""},{"店铺id":"","分类名称":"","商品名称":"","价格":"","餐盒数量":"","餐盒价格":"","最小购买量":"","折扣价格":"","折扣限购":""},{"店铺id":"","分类名称":"","商品名称":"","价格":"","餐盒数量":"","餐盒价格":"","最小购买量":"","折扣价格":"","折扣限购":""},{"店铺id":"","分类名称":"","商品名称":"","价格":"","餐盒数量":"","餐盒价格":"","最小购买量":"","折扣价格":"","折扣限购":""},{"店铺id":"","分类名称":"","商品名称":"","价格":"","餐盒数量":"","餐盒价格":"","最小购买量":"","折扣价格":"","折扣限购":""},{"店铺id":"","分类名称":"","商品名称":"","价格":"","餐盒数量":"","餐盒价格":"","最小购买量":"","折扣价格":"","折扣限购":""},{"店铺id":"","分类名称":"","商品名称":"","价格":"","餐盒数量":"","餐盒价格":"","最小购买量":"","折扣价格":"","折扣限购":""},{"店铺id":"","分类名称":"","商品名称":"","价格":"","餐盒数量":"","餐盒价格":"","最小购买量":"","折扣价格":"","折扣限购":""},{"店铺id":"","分类名称":"","商品名称":"","价格":"","餐盒数量":"","餐盒价格":"","最小购买量":"","折扣价格":"","折扣限购":""},{"店铺id":"","分类名称":"","商品名称":"","价格":"","餐盒数量":"","餐盒价格":"","最小购买量":"","折扣价格":"","折扣限购":""},{"店铺id":"","分类名称":"","商品名称":"","价格":"","餐盒数量":"","餐盒价格":"","最小购买量":"","折扣价格":"","折扣限购":""},{"店铺id":"","分类名称":"","商品名称":"","价格":"","餐盒数量":"","餐盒价格":"","最小购买量":"","折扣价格":"","折扣限购":""},{"店铺id":"","分类名称":"","商品名称":"","价格":"","餐盒数量":"","餐盒价格":"","最小购买量":"","折扣价格":"","折扣限购":""},{"店铺id":"","分类名称":"","商品名称":"","价格":"","餐盒数量":"","餐盒价格":"","最小购买量":"","折扣价格":"","折扣限购":""},{"店铺id":"","分类名称":"","商品名称":"","价格":"","餐盒数量":"","餐盒价格":"","最小购买量":"","折扣价格":"","折扣限购":""},{"店铺id":"","分类名称":"","商品名称":"","价格":"","餐盒数量":"","餐盒价格":"","最小购买量":"","折扣价格":"","折扣限购":""},{"店铺id":"","分类名称":"","商品名称":"","价格":"","餐盒数量":"","餐盒价格":"","最小购买量":"","折扣价格":"","折扣限购":""},{"店铺id":"","分类名称":"","商品名称":"","价格":"","餐盒数量":"","餐盒价格":"","最小购买量":"","折扣价格":"","折扣限购":""},{"店铺id":"","分类名称":"","商品名称":"","价格":"","餐盒数量":"","餐盒价格":"","最小购买量":"","折扣价格":"","折扣限购":""},{"店铺id":"","分类名称":"","商品名称":"","价格":"","餐盒数量":"","餐盒价格":"","最小购买量":"","折扣价格":"","折扣限购":""},{"店铺id":"","分类名称":"","商品名称":"","价格":"","餐盒数量":"","餐盒价格":"","最小购买量":"","折扣价格":"","折扣限购":""},{"店铺id":"","分类名称":"","商品名称":"","价格":"","餐盒数量":"","餐盒价格":"","最小购买量":"","折扣价格":"","折扣限购":""},{"店铺id":"","分类名称":"","商品名称":"","价格":"","餐盒数量":"","餐盒价格":"","最小购买量":"","折扣价格":"","折扣限购":""},{"店铺id":"","分类名称":"","商品名称":"","价格":"","餐盒数量":"","餐盒价格":"","最小购买量":"","折扣价格":"","折扣限购":""},{"店铺id":"","分类名称":"","商品名称":"","价格":"","餐盒数量":"","餐盒价格":"","最小购买量":"","折扣价格":"","折扣限购":""},{"店铺id":"","分类名称":"","商品名称":"","价格":"","餐盒数量":"","餐盒价格":"","最小购买量":"","折扣价格":"","折扣限购":""},{"店铺id":"","分类名称":"","商品名称":"","价格":"","餐盒数量":"","餐盒价格":"","最小购买量":"","折扣价格":"","折扣限购":""},{"店铺id":"","分类名称":"","商品名称":"","价格":"","餐盒数量":"","餐盒价格":"","最小购买量":"","折扣价格":"","折扣限购":""},{"店铺id":"","分类名称":"","商品名称":"","价格":"","餐盒数量":"","餐盒价格":"","最小购买量":"","折扣价格":"","折扣限购":""},{"店铺id":"","分类名称":"","商品名称":"","价格":"","餐盒数量":"","餐盒价格":"","最小购买量":"","折扣价格":"","折扣限购":""},{"店铺id":"","分类名称":"","商品名称":"","价格":"","餐盒数量":"","餐盒价格":"","最小购买量":"","折扣价格":"","折扣限购":""},{"店铺id":"","分类名称":"","商品名称":"","价格":"","餐盒数量":"","餐盒价格":"","最小购买量":"","折扣价格":"","折扣限购":""},{"店铺id":"","分类名称":"","商品名称":"","价格":"","餐盒数量":"","餐盒价格":"","最小购买量":"","折扣价格":"","折扣限购":""},{"店铺id":"","分类名称":"","商品名称":"","价格":"","餐盒数量":"","餐盒价格":"","最小购买量":"","折扣价格":"","折扣限购":""},{"店铺id":"","分类名称":"","商品名称":"","价格":"","餐盒数量":"","餐盒价格":"","最小购买量":"","折扣价格":"","折扣限购":""},{"店铺id":"","分类名称":"","商品名称":"","价格":"","餐盒数量":"","餐盒价格":"","最小购买量":"","折扣价格":"","折扣限购":""},{"店铺id":"","分类名称":"","商品名称":"","价格":"","餐盒数量":"","餐盒价格":"","最小购买量":"","折扣价格":"","折扣限购":""},{"店铺id":"","分类名称":"","商品名称":"","价格":"","餐盒数量":"","餐盒价格":"","最小购买量":"","折扣价格":"","折扣限购":""},{"店铺id":"","分类名称":"","商品名称":"","价格":"","餐盒数量":"","餐盒价格":"","最小购买量":"","折扣价格":"","折扣限购":""},{"店铺id":"","分类名称":"","商品名称":"","价格":"","餐盒数量":"","餐盒价格":"","最小购买量":"","折扣价格":"","折扣限购":""},{"店铺id":"","分类名称":"","商品名称":"","价格":"","餐盒数量":"","餐盒价格":"","最小购买量":"","折扣价格":"","折扣限购":""},{"店铺id":"","分类名称":"","商品名称":"","价格":"","餐盒数量":"","餐盒价格":"","最小购买量":"","折扣价格":"","折扣限购":""},{"店铺id":"","分类名称":"","商品名称":"","价格":"","餐盒数量":"","餐盒价格":"","最小购买量":"","折扣价格":"","折扣限购":""},{"店铺id":"","分类名称":"","商品名称":"","价格":"","餐盒数量":"","餐盒价格":"","最小购买量":"","折扣价格":"","折扣限购":""},{"店铺id":"","分类名称":"","商品名称":"","价格":"","餐盒数量":"","餐盒价格":"","最小购买量":"","折扣价格":"","折扣限购":""},{"店铺id":"","分类名称":"","商品名称":"","价格":"","餐盒数量":"","餐盒价格":"","最小购买量":"","折扣价格":"","折扣限购":""},{"店铺id":"","分类名称":"","商品名称":"","价格":"","餐盒数量":"","餐盒价格":"","最小购买量":"","折扣价格":"","折扣限购":""},{"店铺id":"","分类名称":"","商品名称":"","价格":"","餐盒数量":"","餐盒价格":"","最小购买量":"","折扣价格":"","折扣限购":""},{"店铺id":"","分类名称":"","商品名称":"","价格":"","餐盒数量":"","餐盒价格":"","最小购买量":"","折扣价格":"","折扣限购":""},{"店铺id":"","分类名称":"","商品名称":"","价格":"","餐盒数量":"","餐盒价格":"","最小购买量":"","折扣价格":"","折扣限购":""},{"店铺id":"","分类名称":"","商品名称":"","价格":"","餐盒数量":"","餐盒价格":"","最小购买量":"","折扣价格":"","折扣限购":""},{"店铺id":"","分类名称":"","商品名称":"","价格":"","餐盒数量":"","餐盒价格":"","最小购买量":"","折扣价格":"","折扣限购":""},{"店铺id":"","分类名称":"","商品名称":"","价格":"","餐盒数量":"","餐盒价格":"","最小购买量":"","折扣价格":"","折扣限购":""},{"店铺id":"","分类名称":"","商品名称":"","价格":"","餐盒数量":"","餐盒价格":"","最小购买量":"","折扣价格":"","折扣限购":""},{"店铺id":"","分类名称":"","商品名称":"","价格":"","餐盒数量":"","餐盒价格":"","最小购买量":"","折扣价格":"","折扣限购":""},{"店铺id":"","分类名称":"","商品名称":"","价格":"","餐盒数量":"","餐盒价格":"","最小购买量":"","折扣价格":"","折扣限购":""},{"店铺id":"","分类名称":"","商品名称":"","价格":"","餐盒数量":"","餐盒价格":"","最小购买量":"","折扣价格":"","折扣限购":""},{"店铺id":"","分类名称":"","商品名称":"","价格":"","餐盒数量":"","餐盒价格":"","最小购买量":"","折扣价格":"","折扣限购":""},{"店铺id":"","分类名称":"","商品名称":"","价格":"","餐盒数量":"","餐盒价格":"","最小购买量":"","折扣价格":"","折扣限购":""},{"店铺id":"","分类名称":"","商品名称":"","价格":"","餐盒数量":"","餐盒价格":"","最小购买量":"","折扣价格":"","折扣限购":""},{"店铺id":"","分类名称":"","商品名称":"","价格":"","餐盒数量":"","餐盒价格":"","最小购买量":"","折扣价格":"","折扣限购":""},{"店铺id":"","分类名称":"","商品名称":"","价格":"","餐盒数量":"","餐盒价格":"","最小购买量":"","折扣价格":"","折扣限购":""},{"店铺id":"","分类名称":"","商品名称":"","价格":"","餐盒数量":"","餐盒价格":"","最小购买量":"","折扣价格":"","折扣限购":""},{"店铺id":"","分类名称":"","商品名称":"","价格":"","餐盒数量":"","餐盒价格":"","最小购买量":"","折扣价格":"","折扣限购":""},{"店铺id":"","分类名称":"","商品名称":"","价格":"","餐盒数量":"","餐盒价格":"","最小购买量":"","折扣价格":"","折扣限购":""},{"店铺id":"","分类名称":"","商品名称":"","价格":"","餐盒数量":"","餐盒价格":"","最小购买量":"","折扣价格":"","折扣限购":""},{"店铺id":"","分类名称":"","商品名称":"","价格":"","餐盒数量":"","餐盒价格":"","最小购买量":"","折扣价格":"","折扣限购":""},{"店铺id":"","分类名称":"","商品名称":"","价格":"","餐盒数量":"","餐盒价格":"","最小购买量":"","折扣价格":"","折扣限购":""},{"店铺id":"","分类名称":"","商品名称":"","价格":"","餐盒数量":"","餐盒价格":"","最小购买量":"","折扣价格":"","折扣限购":""},{"店铺id":"","分类名称":"","商品名称":"","价格":"","餐盒数量":"","餐盒价格":"","最小购买量":"","折扣价格":"","折扣限购":""},{"店铺id":"","分类名称":"","商品名称":"","价格":"","餐盒数量":"","餐盒价格":"","最小购买量":"","折扣价格":"","折扣限购":""},{"店铺id":"","分类名称":"","商品名称":"","价格":"","餐盒数量":"","餐盒价格":"","最小购买量":"","折扣价格":"","折扣限购":""},{"店铺id":"","分类名称":"","商品名称":"","价格":"","餐盒数量":"","餐盒价格":"","最小购买量":"","折扣价格":"","折扣限购":""},{"店铺id":"","分类名称":"","商品名称":"","价格":"","餐盒数量":"","餐盒价格":"","最小购买量":"","折扣价格":"","折扣限购":""},{"店铺id":"","分类名称":"","商品名称":"","价格":"","餐盒数量":"","餐盒价格":"","最小购买量":"","折扣价格":"","折扣限购":""},{"店铺id":"","分类名称":"","商品名称":"","价格":"","餐盒数量":"","餐盒价格":"","最小购买量":"","折扣价格":"","折扣限购":""},{"店铺id":"","分类名称":"","商品名称":"","价格":"","餐盒数量":"","餐盒价格":"","最小购买量":"","折扣价格":"","折扣限购":""},{"店铺id":"","分类名称":"","商品名称":"","价格":"","餐盒数量":"","餐盒价格":"","最小购买量":"","折扣价格":"","折扣限购":""},{"店铺id":"","分类名称":"","商品名称":"","价格":"","餐盒数量":"","餐盒价格":"","最小购买量":"","折扣价格":"","折扣限购":""},{"店铺id":"","分类名称":"","商品名称":"","价格":"","餐盒数量":"","餐盒价格":"","最小购买量":"","折扣价格":"","折扣限购":""},{"店铺id":"","分类名称":"","商品名称":"","价格":"","餐盒数量":"","餐盒价格":"","最小购买量":"","折扣价格":"","折扣限购":""},{"店铺id":"","分类名称":"","商品名称":"","价格":"","餐盒数量":"","餐盒价格":"","最小购买量":"","折扣价格":"","折扣限购":""},{"店铺id":"","分类名称":"","商品名称":"","价格":"","餐盒数量":"","餐盒价格":"","最小购买量":"","折扣价格":"","折扣限购":""},{"店铺id":"","分类名称":"","商品名称":"","价格":"","餐盒数量":"","餐盒价格":"","最小购买量":"","折扣价格":"","折扣限购":""},{"店铺id":"","分类名称":"","商品名称":"","价格":"","餐盒数量":"","餐盒价格":"","最小购买量":"","折扣价格":"","折扣限购":""},{"店铺id":"","分类名称":"","商品名称":"","价格":"","餐盒数量":"","餐盒价格":"","最小购买量":"","折扣价格":"","折扣限购":""},{"店铺id":"","分类名称":"","商品名称":"","价格":"","餐盒数量":"","餐盒价格":"","最小购买量":"","折扣价格":"","折扣限购":""},{"店铺id":"","分类名称":"","商品名称":"","价格":"","餐盒数量":"","餐盒价格":"","最小购买量":"","折扣价格":"","折扣限购":""},{"店铺id":"","分类名称":"","商品名称":"","价格":"","餐盒数量":"","餐盒价格":"","最小购买量":"","折扣价格":"","折扣限购":""},{"店铺id":"","分类名称":"","商品名称":"","价格":"","餐盒数量":"","餐盒价格":"","最小购买量":"","折扣价格":"","折扣限购":""},{"店铺id":"","分类名称":"","商品名称":"","价格":"","餐盒数量":"","餐盒价格":"","最小购买量":"","折扣价格":"","折扣限购":""},{"店铺id":"","分类名称":"","商品名称":"","价格":"","餐盒数量":"","餐盒价格":"","最小购买量":"","折扣价格":"","折扣限购":""},{"店铺id":"","分类名称":"","商品名称":"","价格":"","餐盒数量":"","餐盒价格":"","最小购买量":"","折扣价格":"","折扣限购":""},{"店铺id":"","分类名称":"","商品名称":"","价格":"","餐盒数量":"","餐盒价格":"","最小购买量":"","折扣价格":"","折扣限购":""},{"店铺id":"","分类名称":"","商品名称":"","价格":"","餐盒数量":"","餐盒价格":"","最小购买量":"","折扣价格":"","折扣限购":""},{"店铺id":"","分类名称":"","商品名称":"","价格":"","餐盒数量":"","餐盒价格":"","最小购买量":"","折扣价格":"","折扣限购":""},{"店铺id":"","分类名称":"","商品名称":"","价格":"","餐盒数量":"","餐盒价格":"","最小购买量":"","折扣价格":"","折扣限购":""},{"店铺id":"","分类名称":"","商品名称":"","价格":"","餐盒数量":"","餐盒价格":"","最小购买量":"","折扣价格":"","折扣限购":""},{"店铺id":"","分类名称":"","商品名称":"","价格":"","餐盒数量":"","餐盒价格":"","最小购买量":"","折扣价格":"","折扣限购":""},{"店铺id":"","分类名称":"","商品名称":"","价格":"","餐盒数量":"","餐盒价格":"","最小购买量":"","折扣价格":"","折扣限购":""},{"店铺id":"","分类名称":"","商品名称":"","价格":"","餐盒数量":"","餐盒价格":"","最小购买量":"","折扣价格":"","折扣限购":""},{"店铺id":"","分类名称":"","商品名称":"","价格":"","餐盒数量":"","餐盒价格":"","最小购买量":"","折扣价格":"","折扣限购":""},{"店铺id":"","分类名称":"","商品名称":"","价格":"","餐盒数量":"","餐盒价格":"","最小购买量":"","折扣价格":"","折扣限购":""},{"店铺id":"","分类名称":"","商品名称":"","价格":"","餐盒数量":"","餐盒价格":"","最小购买量":"","折扣价格":"","折扣限购":""},{"店铺id":"","分类名称":"","商品名称":"","价格":"","餐盒数量":"","餐盒价格":"","最小购买量":"","折扣价格":"","折扣限购":""},{"店铺id":"","分类名称":"","商品名称":"","价格":"","餐盒数量":"","餐盒价格":"","最小购买量":"","折扣价格":"","折扣限购":""},{"店铺id":"","分类名称":"","商品名称":"","价格":"","餐盒数量":"","餐盒价格":"","最小购买量":"","折扣价格":"","折扣限购":""},{"店铺id":"","分类名称":"","商品名称":"","价格":"","餐盒数量":"","餐盒价格":"","最小购买量":"","折扣价格":"","折扣限购":""},{"店铺id":"","分类名称":"","商品名称":"","价格":"","餐盒数量":"","餐盒价格":"","最小购买量":"","折扣价格":"","折扣限购":""},{"店铺id":"","分类名称":"","商品名称":"","价格":"","餐盒数量":"","餐盒价格":"","最小购买量":"","折扣价格":"","折扣限购":""},{"店铺id":"","分类名称":"","商品名称":"","价格":"","餐盒数量":"","餐盒价格":"","最小购买量":"","折扣价格":"","折扣限购":""},{"店铺id":"","分类名称":"","商品名称":"","价格":"","餐盒数量":"","餐盒价格":"","最小购买量":"","折扣价格":"","折扣限购":""}]